[{"caption":"Model No. Description \n\nROUGE-L Content F1 \n\n1 \nRandom Baseline using Language Model \n27.5 \n8.3 \n2a \nRule-based Extractive summary \n16.4 \n18.8 \n2b \nNext-neighbor Summary \n31.8 \n17.9 \n\n3 \nUsing Extracted Sentence from 2a only (Text-only) \n46.4 \n36.0 \n4 \nFirst 200 tokens (Text-only) \n40.3 \n27.5 \n5a \nS2S Complete Transcript (Text-only, 650 tokens) \n53.9 \n47.4 \n5b \nPG Complete Transcript (Text-only) \n50.2 \n42.0 \n5c \nASR output Complete Transcript (Text-only) \n46.1 \n34.7 \n\n6 \nAction Features only (Video) \n38.5 \n24.8 \n7 \nAction Features + RNN (Video) \n46.3 \n34.9 \n\n8 \nGround-truth transcript + Action with Hierarchical Attn \n54.9 \n48.9 \n9 \nASR output + Action with Hierarchical Attn \n46.3 \n34.7 \n\nTable 1: ROUGE-L and Content F1 for different summarization models: random baseline (1), rule-based extracted \nsummary (2a), nearest neighbor summary (2b), different text-only (3,4,5a), pointer-generator (5b), ASR output \ntranscript (5c), video-only (6-7) and text-and-video models (8-9). \n\n","rows":["Rule - based Extractive summary","PG Complete Transcript ( Text - only )","First 200 tokens ( Text - only )","5a","Random Baseline using Language Model","5b","5c","2a","2b","Action Features + RNN ( Video )","1","3","4","ASR output Complete Transcript ( Text - only )","6","ASR output + Action with Hierarchical Attn","Next - neighbor Summary","Using Extracted Sentence from 2a only ( Text - only )","7","S2S Complete Transcript ( Text - only , 650 tokens )","8","Ground - truth transcript + Action with Hierarchical Attn","Action Features only ( Video )","9"],"columns":["ROUGE - L","Content F1"],"mergedAllColumns":[],"numberCells":[{"number":"34.9","isBolded":true,"associatedRows":["7","Action Features + RNN ( Video )"],"associatedColumns":["Content F1"],"associatedMergedColumns":[]},{"number":"34.7","isBolded":false,"associatedRows":["5c","ASR output Complete Transcript ( Text - only )"],"associatedColumns":["Content F1"],"associatedMergedColumns":[]},{"number":"16.4","isBolded":false,"associatedRows":["2a","Rule - based Extractive summary"],"associatedColumns":["ROUGE - L"],"associatedMergedColumns":[]},{"number":"36.0","isBolded":false,"associatedRows":["3","Using Extracted Sentence from 2a only ( Text - only )"],"associatedColumns":["Content F1"],"associatedMergedColumns":[]},{"number":"46.3","isBolded":false,"associatedRows":["9","ASR output + Action with Hierarchical Attn"],"associatedColumns":["ROUGE - L"],"associatedMergedColumns":[]},{"number":"46.4","isBolded":false,"associatedRows":["3","Using Extracted Sentence from 2a only ( Text - only )"],"associatedColumns":["ROUGE - L"],"associatedMergedColumns":[]},{"number":"18.8","isBolded":false,"associatedRows":["2a","Rule - based Extractive summary"],"associatedColumns":["Content F1"],"associatedMergedColumns":[]},{"number":"46.3","isBolded":true,"associatedRows":["7","Action Features + RNN ( Video )"],"associatedColumns":["ROUGE - L"],"associatedMergedColumns":[]},{"number":"34.7","isBolded":false,"associatedRows":["9","ASR output + Action with Hierarchical Attn"],"associatedColumns":["Content F1"],"associatedMergedColumns":[]},{"number":"47.4","isBolded":true,"associatedRows":["5a","S2S Complete Transcript ( Text - only , 650 tokens )"],"associatedColumns":["Content F1"],"associatedMergedColumns":[]},{"number":"46.1","isBolded":false,"associatedRows":["5c","ASR output Complete Transcript ( Text - only )"],"associatedColumns":["ROUGE - L"],"associatedMergedColumns":[]},{"number":"38.5","isBolded":false,"associatedRows":["6","Action Features only ( Video )"],"associatedColumns":["ROUGE - L"],"associatedMergedColumns":[]},{"number":"50.2","isBolded":false,"associatedRows":["5b","PG Complete Transcript ( Text - only )"],"associatedColumns":["ROUGE - L"],"associatedMergedColumns":[]},{"number":"42.0","isBolded":false,"associatedRows":["5b","PG Complete Transcript ( Text - only )"],"associatedColumns":["Content F1"],"associatedMergedColumns":[]},{"number":"24.8","isBolded":false,"associatedRows":["6","Action Features only ( Video )"],"associatedColumns":["Content F1"],"associatedMergedColumns":[]},{"number":"40.3","isBolded":false,"associatedRows":["4","First 200 tokens ( Text - only )"],"associatedColumns":["ROUGE - L"],"associatedMergedColumns":[]},{"number":"27.5","isBolded":false,"associatedRows":["1","Random Baseline using Language Model"],"associatedColumns":["ROUGE - L"],"associatedMergedColumns":[]},{"number":"27.5","isBolded":false,"associatedRows":["4","First 200 tokens ( Text - only )"],"associatedColumns":["Content F1"],"associatedMergedColumns":[]},{"number":"48.9","isBolded":true,"associatedRows":["8","Ground - truth transcript + Action with Hierarchical Attn"],"associatedColumns":["Content F1"],"associatedMergedColumns":[]},{"number":"8.3","isBolded":false,"associatedRows":["1","Random Baseline using Language Model"],"associatedColumns":["Content F1"],"associatedMergedColumns":[]},{"number":"17.9","isBolded":false,"associatedRows":["2b","Next - neighbor Summary"],"associatedColumns":["Content F1"],"associatedMergedColumns":[]},{"number":"54.9","isBolded":true,"associatedRows":["8","Ground - truth transcript + Action with Hierarchical Attn"],"associatedColumns":["ROUGE - L"],"associatedMergedColumns":[]},{"number":"31.8","isBolded":false,"associatedRows":["2b","Next - neighbor Summary"],"associatedColumns":["ROUGE - L"],"associatedMergedColumns":[]},{"number":"53.9","isBolded":true,"associatedRows":["5a","S2S Complete Transcript ( Text - only , 650 tokens )"],"associatedColumns":["ROUGE - L"],"associatedMergedColumns":[]}]},{"caption":"Table 2: Human evaluation scores on 4 different mea-\nsures of Informativeness (INF), Relevance (REL), Co-\nherence (COH), Fluency (FLU). \n\n","rows":["Text - only ( 5a )"],"columns":["INF","REL","COH","FLU"],"mergedAllColumns":[],"numberCells":[{"number":"3.78","isBolded":true,"associatedRows":["Text - only ( 5a )"],"associatedColumns":["REL"],"associatedMergedColumns":[]},{"number":"3.86","isBolded":false,"associatedRows":["Text - only ( 5a )"],"associatedColumns":["INF"],"associatedMergedColumns":[]},{"number":"3.92","isBolded":false,"associatedRows":["Text - only ( 5a )"],"associatedColumns":["FLU"],"associatedMergedColumns":[]},{"number":"3.78","isBolded":false,"associatedRows":["Text - only ( 5a )"],"associatedColumns":["COH"],"associatedMergedColumns":[]}]}]