[{"caption":"Methods \nMT10 \nMT50 \n\nMulti-task PPO \n25% \n8.98% \nMulti-task TRPO \n29% \n22.86% \nTask embeddings \n30% \n15.31% \nMulti-task SAC \n39.5% \n28.83% \nMulti-task multi-head SAC \n88% \n35.85% \n\nMethods \n\nML10 \nML45 \n\nmeta-train \nmeta-test \nmeta-train \nmeta-test \n\nMAML \n25% \n36% \n21.14% \n23.93% \nRL 2 \n50% \n10% \n43.18% \n20% \nPEARL \n42.78% \n0% \n11.36% \n30% \n\nTable 1: Average success rates over all tasks for MT10, MT50, ML10, and ML45. The best performance in \n\neach benchmark is bolden. For MT10 and MT50, we show the average training success rate and multi-task \nmulti-head SAC outperforms other methods. For ML10 and ML45, we show the meta-train and meta-test \nsuccess rates. RL 2 achieves best meta-train performance in ML10 and ML45, while MAML and PEARL get \nthe best generalization performance in ML10 and ML45 meta-test tasks respectively. \n\n","rows":["Task embeddings","MAML","Multi - task multi - head SAC","PEARL","Multi - task SAC","0%","Multi - task TRPO","Multi - task PPO","RL"],"columns":["MT10","ML45","MT50","meta - test","ML10","Methods","meta - train"],"mergedAllColumns":["2"],"numberCells":[{"number":"22.86%","isBolded":false,"associatedRows":["Multi - task TRPO"],"associatedColumns":["MT50","Methods"],"associatedMergedColumns":[]},{"number":"43.18%","isBolded":true,"associatedRows":["Multi - task SAC","RL"],"associatedColumns":["ML45","meta - train"],"associatedMergedColumns":[]},{"number":"88%","isBolded":true,"associatedRows":["Multi - task multi - head SAC"],"associatedColumns":["MT10","Methods"],"associatedMergedColumns":["2"]},{"number":"10%","isBolded":false,"associatedRows":["Multi - task SAC","RL"],"associatedColumns":["ML10","meta - test"],"associatedMergedColumns":[]},{"number":"28.83%","isBolded":false,"associatedRows":["Multi - task SAC"],"associatedColumns":["MT50","Methods"],"associatedMergedColumns":[]},{"number":"29%","isBolded":false,"associatedRows":["Multi - task TRPO"],"associatedColumns":["MT10","Methods"],"associatedMergedColumns":[]},{"number":"36%","isBolded":true,"associatedRows":["Task embeddings","MAML"],"associatedColumns":["ML10","meta - test"],"associatedMergedColumns":[]},{"number":"42.78%","isBolded":false,"associatedRows":["Multi - task multi - head SAC","PEARL"],"associatedColumns":["ML10","meta - train"],"associatedMergedColumns":["2"]},{"number":"50%","isBolded":true,"associatedRows":["Multi - task SAC","RL"],"associatedColumns":["ML10","meta - train"],"associatedMergedColumns":[]},{"number":"8.98%","isBolded":false,"associatedRows":["Multi - task PPO"],"associatedColumns":["MT50"],"associatedMergedColumns":[]},{"number":"25%","isBolded":false,"associatedRows":["Multi - task PPO"],"associatedColumns":["MT10"],"associatedMergedColumns":[]},{"number":"11.36%","isBolded":false,"associatedRows":["Multi - task multi - head SAC","PEARL","0%"],"associatedColumns":["ML45","meta - train"],"associatedMergedColumns":["2"]},{"number":"30%","isBolded":true,"associatedRows":["Multi - task multi - head SAC","PEARL","0%"],"associatedColumns":["ML45","meta - test"],"associatedMergedColumns":["2"]},{"number":"25%","isBolded":false,"associatedRows":["Task embeddings","MAML"],"associatedColumns":["ML10","meta - train"],"associatedMergedColumns":[]},{"number":"21.14%","isBolded":false,"associatedRows":["Task embeddings","MAML"],"associatedColumns":["ML45","meta - train"],"associatedMergedColumns":[]},{"number":"35.85%","isBolded":true,"associatedRows":["Multi - task multi - head SAC"],"associatedColumns":["MT50","Methods"],"associatedMergedColumns":["2"]},{"number":"30%","isBolded":false,"associatedRows":["Task embeddings"],"associatedColumns":["MT10","Methods"],"associatedMergedColumns":[]},{"number":"20%","isBolded":false,"associatedRows":["Multi - task SAC","RL"],"associatedColumns":["ML45","meta - test"],"associatedMergedColumns":[]},{"number":"39.5%","isBolded":false,"associatedRows":["Multi - task SAC"],"associatedColumns":["MT10","Methods"],"associatedMergedColumns":[]},{"number":"15.31%","isBolded":false,"associatedRows":["Task embeddings"],"associatedColumns":["MT50","Methods"],"associatedMergedColumns":[]},{"number":"23.93%","isBolded":false,"associatedRows":["Task embeddings","MAML"],"associatedColumns":["ML45","meta - test"],"associatedMergedColumns":[]}]}]