[{"caption":"Weights Steps Train Interpolation Extrapolation \nacc \u003e95% acc \u003e95% \nLSTM with thinking steps (Saxton et al.) 18M \n500k \n-\n57.00% \n6 \n41.00% \n1 \nTransformer (Saxton et al.) \n30M \n500k \n-\n76.00% 13 50.00% \n1 \nTransformer (ours) \n44.2M 1000k 86.60% 79.54% 16 53.28% \n2 \nTP-Transformer (ours) \n49.1M 1000k 89.01% 81.92% 18 54.67% \n3 \nTP-Transformer B (ours) \n43.0M 1000k 87.53% 80.52% 16 52.04% \n1 \nTP-Transformer C (ours) \n30.0M 1000k 86.33% 79.02% 14 54.71% \n1 \n\nTable 1: Model accuracy averaged over all modules. A sample is correct if all characters of the target sequence have \nbeen predicted correctly. The column \"\u003e95%\" counts how many of the 56 modules achieve over 95% accuracy. \nTP-Transformer B and C differ from the standard hyper-parameters in order to reduce the total number of weights. \nSee section 4.1 for more details. \n\n","rows":["13","TP - Transformer ( ours )","LSTM with thinking steps ( Saxton et al . )","14","1000k","16","18M","18","TP - Transformer B ( ours )","See section","-","500k","30M","Transformer ( Saxton et al . )","Transformer ( ours )","6","TP - Transformer C ( ours )"],"columns":["acc","Interpolation","Extrapolation","Weights","Train"],"mergedAllColumns":["1","2","3","TP - Transformer B and C differ from the standard hyper - parameters in order to reduce the total number of weights ."],"numberCells":[{"number":"87.53%","isBolded":false,"associatedRows":["TP - Transformer B ( ours )","30M","1000k"],"associatedColumns":["Train","acc"],"associatedMergedColumns":["3"]},{"number":"80.52%","isBolded":false,"associatedRows":["TP - Transformer B ( ours )","30M","1000k","-"],"associatedColumns":["Interpolation","acc"],"associatedMergedColumns":["3"]},{"number":"54.67%","isBolded":false,"associatedRows":["TP - Transformer ( ours )","30M","1000k","-","18"],"associatedColumns":["Extrapolation","acc"],"associatedMergedColumns":["2"]},{"number":"43.0M","isBolded":false,"associatedRows":["TP - Transformer B ( ours )"],"associatedColumns":["Weights","acc"],"associatedMergedColumns":["3"]},{"number":"57.00%","isBolded":false,"associatedRows":["LSTM with thinking steps ( Saxton et al . )","18M","500k","-"],"associatedColumns":["Interpolation","acc"],"associatedMergedColumns":[]},{"number":"54.71%","isBolded":false,"associatedRows":["TP - Transformer C ( ours )","30M","1000k","-","14"],"associatedColumns":["Extrapolation","acc"],"associatedMergedColumns":["1"]},{"number":"76.00%","isBolded":false,"associatedRows":["Transformer ( Saxton et al . )","30M","500k","-"],"associatedColumns":["Interpolation","acc"],"associatedMergedColumns":["1"]},{"number":"50.00%","isBolded":false,"associatedRows":["Transformer ( Saxton et al . )","30M","500k","-","13"],"associatedColumns":["Extrapolation","acc"],"associatedMergedColumns":["1"]},{"number":"86.60%","isBolded":false,"associatedRows":["Transformer ( ours )","30M","1000k"],"associatedColumns":["Train","acc"],"associatedMergedColumns":["1"]},{"number":"81.92%","isBolded":false,"associatedRows":["TP - Transformer ( ours )","30M","1000k","-"],"associatedColumns":["Interpolation","acc"],"associatedMergedColumns":["2"]},{"number":"79.02%","isBolded":false,"associatedRows":["TP - Transformer C ( ours )","30M","1000k","-"],"associatedColumns":["Interpolation","acc"],"associatedMergedColumns":["1"]},{"number":"44.2M","isBolded":false,"associatedRows":["Transformer ( ours )"],"associatedColumns":["Weights","acc"],"associatedMergedColumns":["1"]},{"number":"79.54%","isBolded":false,"associatedRows":["Transformer ( ours )","30M","1000k","-"],"associatedColumns":["Interpolation","acc"],"associatedMergedColumns":["1"]},{"number":"49.1M","isBolded":false,"associatedRows":["TP - Transformer ( ours )"],"associatedColumns":["Weights","acc"],"associatedMergedColumns":["2"]},{"number":"4.1formoredetails.","isBolded":false,"associatedRows":["See section"],"associatedColumns":["Weights","acc"],"associatedMergedColumns":["TP - Transformer B and C differ from the standard hyper - parameters in order to reduce the total number of weights ."]},{"number":"52.04%","isBolded":false,"associatedRows":["TP - Transformer B ( ours )","30M","1000k","-","16"],"associatedColumns":["Extrapolation","acc"],"associatedMergedColumns":["3"]},{"number":"86.33%","isBolded":false,"associatedRows":["TP - Transformer C ( ours )","30M","1000k"],"associatedColumns":["Train","acc"],"associatedMergedColumns":["1"]},{"number":"30.0M","isBolded":false,"associatedRows":["TP - Transformer C ( ours )"],"associatedColumns":["Weights","acc"],"associatedMergedColumns":["1"]},{"number":"41.00%","isBolded":false,"associatedRows":["LSTM with thinking steps ( Saxton et al . )","18M","500k","-","6"],"associatedColumns":["Extrapolation","acc"],"associatedMergedColumns":[]},{"number":"53.28%","isBolded":false,"associatedRows":["Transformer ( ours )","30M","1000k","-","16"],"associatedColumns":["Extrapolation","acc"],"associatedMergedColumns":["1"]},{"number":"89.01%","isBolded":false,"associatedRows":["TP - Transformer ( ours )","30M","1000k"],"associatedColumns":["Train","acc"],"associatedMergedColumns":["2"]}]}]