[{"caption":"Thus \nevery 16 × 16 block of the 32 × 32 query image attends with \nfull information to the 16 × 16 key image. \n\n# Heads FID \nInception \nSAGAN \n1 \n18.65 52.52 \nSAGAN \n8 \n20.09 46.01 \nYLG-SAGAN \n8 \n15.94 57.22 \nYLG -No ESA 8 \n17.47 51.09 \nYLG -Strided \n8 \n16.64 55.21 \n\nTable 1: ImageNet Results: Table of results after training SAGAN \n\nand YLG-SAGAN on ImageNet. Table also includes Ablation Studies \n(SAGAN 8 heads, YLG -No ESA, YLG -Strided). Our best model, YLG, \nachieves 15.94 FID and 57.22 Inception score. Our scores correspond to \n14.53% and 8.95% improvement to FID and Inception respectively. We \nemphasize that these benefits are obtained by only one layer change to \nSAGAN, replacing dense attention with the local sparse attention layer \nthat we introduce. \n\n","rows":["1","YLG - SAGAN","SAGAN","YLG - No ESA","8","achieves","YLG - Strided"],"columns":["FID","Table of results after training SAGAN","Table also includes Ablation Studies","and YLG - SAGAN on ImageNet .","Thus","Inception","Table 1 :","ImageNet Results :","# Heads"],"mergedAllColumns":["( SAGAN 8 heads , YLG - No ESA , YLG - Strided ) . Our best model , YLG ,","full information to the 16 × 16 key image ."],"numberCells":[{"number":"20.09","isBolded":false,"associatedRows":["SAGAN","8"],"associatedColumns":["Thus","FID"],"associatedMergedColumns":["full information to the 16 × 16 key image ."]},{"number":"57.22Inceptionscore.Ourscorescorrespondto","isBolded":true,"associatedRows":["achieves"],"associatedColumns":["Thus","Inception","Table of results after training SAGAN","Table also includes Ablation Studies"],"associatedMergedColumns":["( SAGAN 8 heads , YLG - No ESA , YLG - Strided ) . Our best model , YLG ,"]},{"number":"14.53%and","isBolded":true,"associatedRows":[],"associatedColumns":["Thus","# Heads","Table 1 :","and YLG - SAGAN on ImageNet ."],"associatedMergedColumns":["( SAGAN 8 heads , YLG - No ESA , YLG - Strided ) . Our best model , YLG ,"]},{"number":"15.94","isBolded":true,"associatedRows":["YLG - SAGAN","8"],"associatedColumns":["Thus","FID"],"associatedMergedColumns":["full information to the 16 × 16 key image ."]},{"number":"18.65","isBolded":false,"associatedRows":["SAGAN","1"],"associatedColumns":["Thus","FID"],"associatedMergedColumns":["full information to the 16 × 16 key image ."]},{"number":"57.22","isBolded":true,"associatedRows":["YLG - SAGAN","8"],"associatedColumns":["Thus","Inception"],"associatedMergedColumns":["full information to the 16 × 16 key image ."]},{"number":"8.95%improvementtoFIDandInceptionrespectively.We","isBolded":true,"associatedRows":["achieves"],"associatedColumns":["Thus","Inception","Table of results after training SAGAN","Table also includes Ablation Studies"],"associatedMergedColumns":["( SAGAN 8 heads , YLG - No ESA , YLG - Strided ) . Our best model , YLG ,"]},{"number":"51.09","isBolded":false,"associatedRows":["YLG - No ESA","8"],"associatedColumns":["Thus","Inception"],"associatedMergedColumns":["full information to the 16 × 16 key image ."]},{"number":"55.21","isBolded":false,"associatedRows":["YLG - Strided","8"],"associatedColumns":["Thus","Inception"],"associatedMergedColumns":["full information to the 16 × 16 key image ."]},{"number":"15.94FIDand","isBolded":true,"associatedRows":["achieves"],"associatedColumns":["Thus","# Heads","ImageNet Results :","and YLG - SAGAN on ImageNet ."],"associatedMergedColumns":["( SAGAN 8 heads , YLG - No ESA , YLG - Strided ) . Our best model , YLG ,"]},{"number":"17.47","isBolded":false,"associatedRows":["YLG - No ESA","8"],"associatedColumns":["Thus","FID"],"associatedMergedColumns":["full information to the 16 × 16 key image ."]},{"number":"46.01","isBolded":false,"associatedRows":["SAGAN","8"],"associatedColumns":["Thus","Inception"],"associatedMergedColumns":["full information to the 16 × 16 key image ."]},{"number":"52.52","isBolded":false,"associatedRows":["SAGAN","1"],"associatedColumns":["Thus","Inception"],"associatedMergedColumns":["full information to the 16 × 16 key image ."]},{"number":"16.64","isBolded":false,"associatedRows":["YLG - Strided","8"],"associatedColumns":["Thus","FID"],"associatedMergedColumns":["full information to the 16 × 16 key image ."]}]}]