[{"caption":"Model \nAll \nNo UNK ? \nRNNencdec-30 13.93 \n24.19 \nRNNsearch-30 21.50 \n31.44 \nRNNencdec-50 17.82 \n26.71 \nRNNsearch-50 26.75 \n34.16 \nRNNsearch-50 \n28.45 \n36.15 \nMoses \n33.30 \n35.63 \n\nTable 1: BLEU scores of the trained models com-\nputed on the test set. The second and third columns \nshow respectively the scores on all the sentences and, \non the sentences without any unknown word in them-\nselves and in the reference translations. Note that \nRNNsearch-50 was trained much longer until the \nperformance on the development set stopped improv-\ning. (?) We disallowed the models to generate [UNK]  tokens when only the sentences having no unknown \nwords were evaluated (last column). \n\n","rows":["RNNencdec - 50","RNNsearch - 50","Moses","RNNencdec - 30","RNNsearch - 30"],"columns":["All","No UNK","Table 1 :","selves and in the reference translations .","RNNsearch - 50"],"mergedAllColumns":["on the sentences without any unknown word in them -","show respectively the scores on all the sentences and ,","performance on the development set stopped improv -"],"numberCells":[{"number":"28.45","isBolded":false,"associatedRows":["RNNsearch - 50"],"associatedColumns":["Table 1 :","All","selves and in the reference translations .","RNNsearch - 50"],"associatedMergedColumns":["on the sentences without any unknown word in them -"]},{"number":"21.50","isBolded":false,"associatedRows":["RNNsearch - 30"],"associatedColumns":["Table 1 :","All"],"associatedMergedColumns":["show respectively the scores on all the sentences and ,"]},{"number":"17.82","isBolded":false,"associatedRows":["RNNencdec - 50"],"associatedColumns":["Table 1 :","All"],"associatedMergedColumns":["on the sentences without any unknown word in them -"]},{"number":"26.71","isBolded":false,"associatedRows":["RNNencdec - 50"],"associatedColumns":["Table 1 :","No UNK"],"associatedMergedColumns":["on the sentences without any unknown word in them -"]},{"number":"31.44","isBolded":false,"associatedRows":["RNNsearch - 30"],"associatedColumns":["Table 1 :","No UNK"],"associatedMergedColumns":["show respectively the scores on all the sentences and ,"]},{"number":"34.16","isBolded":false,"associatedRows":["RNNsearch - 50"],"associatedColumns":["Table 1 :","No UNK","selves and in the reference translations ."],"associatedMergedColumns":["on the sentences without any unknown word in them -"]},{"number":"26.75","isBolded":false,"associatedRows":["RNNsearch - 50"],"associatedColumns":["Table 1 :","All","selves and in the reference translations ."],"associatedMergedColumns":["on the sentences without any unknown word in them -"]},{"number":"36.15","isBolded":false,"associatedRows":["RNNsearch - 50"],"associatedColumns":["Table 1 :","No UNK","selves and in the reference translations .","RNNsearch - 50"],"associatedMergedColumns":["on the sentences without any unknown word in them -"]},{"number":"35.63","isBolded":false,"associatedRows":["Moses"],"associatedColumns":["Table 1 :","No UNK","selves and in the reference translations .","RNNsearch - 50"],"associatedMergedColumns":["performance on the development set stopped improv -"]},{"number":"33.30","isBolded":false,"associatedRows":["Moses"],"associatedColumns":["Table 1 :","All","selves and in the reference translations .","RNNsearch - 50"],"associatedMergedColumns":["performance on the development set stopped improv -"]},{"number":"13.93","isBolded":false,"associatedRows":["RNNencdec - 30"],"associatedColumns":["Table 1 :","All"],"associatedMergedColumns":[]},{"number":"24.19","isBolded":false,"associatedRows":["RNNencdec - 30"],"associatedColumns":["Table 1 :","No UNK"],"associatedMergedColumns":[]}]},{"caption":"Model \nUpdates (?10 5 ) Epochs Hours \nGPU \nTrain NLL Dev. NLL \nRNNenc-30 \n8.46 \n6.4 \n109 \n\nTITAN BLACK \n\n28.1 \n53.0 \nRNNenc-50 \n6.00 \n4.5 \n108 \n\nQuadro K-6000 \n\n44.0 \n43.6 \nRNNsearch-30 \n4.71 \n3.6 \n113 \n\nTITAN BLACK \n\n26.7 \n47.2 \nRNNsearch-50 \n2.88 \n2.2 \n111 \n\nQuadro K-6000 \n\n40.7 \n38.1 \nRNNsearch-50 \n6.67 \n5.0 \n252 \n\nQuadro K-6000 \n\n36.7 \n35.2 \n\nTable 2: Learning statistics and relevant information. Each update corresponds to updating the \nparameters once using a single minibatch. One epoch is one pass through the training set. NLL is \nthe average conditional log-probabilities of the sentences in either the training set or the development \nset. Note that the lengths of the sentences differ. \n\n","rows":["RNNenc - 50","111","113","TITAN BLACK","108","Quadro K - 6000","109","RNNsearch - 50","RNNenc - 30","RNNsearch - 30","252"],"columns":["Updates ( ?10","Epochs","Train NLL","Dev . NLL"],"mergedAllColumns":[],"numberCells":[{"number":"4.71","isBolded":false,"associatedRows":["RNNsearch - 30"],"associatedColumns":["Updates ( ?10"],"associatedMergedColumns":[]},{"number":"5.0","isBolded":false,"associatedRows":["RNNsearch - 50"],"associatedColumns":["Epochs"],"associatedMergedColumns":[]},{"number":"6.00","isBolded":false,"associatedRows":["RNNenc - 50"],"associatedColumns":["Updates ( ?10"],"associatedMergedColumns":[]},{"number":"4.5","isBolded":false,"associatedRows":["RNNenc - 50"],"associatedColumns":["Epochs"],"associatedMergedColumns":[]},{"number":"43.6","isBolded":false,"associatedRows":["RNNenc - 50","108","Quadro K - 6000"],"associatedColumns":["Dev . NLL"],"associatedMergedColumns":[]},{"number":"35.2","isBolded":false,"associatedRows":["RNNsearch - 50","252","Quadro K - 6000"],"associatedColumns":["Dev . NLL"],"associatedMergedColumns":[]},{"number":"6.4","isBolded":false,"associatedRows":["RNNenc - 30"],"associatedColumns":["Epochs"],"associatedMergedColumns":[]},{"number":"53.0","isBolded":false,"associatedRows":["RNNenc - 30","109","TITAN BLACK"],"associatedColumns":["Dev . NLL"],"associatedMergedColumns":[]},{"number":"38.1","isBolded":false,"associatedRows":["RNNsearch - 50","111","Quadro K - 6000"],"associatedColumns":["Dev . NLL"],"associatedMergedColumns":[]},{"number":"2.88","isBolded":false,"associatedRows":["RNNsearch - 50"],"associatedColumns":["Updates ( ?10"],"associatedMergedColumns":[]},{"number":"36.7","isBolded":false,"associatedRows":["RNNsearch - 50","252","Quadro K - 6000"],"associatedColumns":["Train NLL"],"associatedMergedColumns":[]},{"number":"47.2","isBolded":false,"associatedRows":["RNNsearch - 30","113","TITAN BLACK"],"associatedColumns":["Dev . NLL"],"associatedMergedColumns":[]},{"number":"28.1","isBolded":false,"associatedRows":["RNNenc - 30","109","TITAN BLACK"],"associatedColumns":["Train NLL"],"associatedMergedColumns":[]},{"number":"44.0","isBolded":false,"associatedRows":["RNNenc - 50","108","Quadro K - 6000"],"associatedColumns":["Train NLL"],"associatedMergedColumns":[]},{"number":"2.2","isBolded":false,"associatedRows":["RNNsearch - 50"],"associatedColumns":["Epochs"],"associatedMergedColumns":[]},{"number":"26.7","isBolded":false,"associatedRows":["RNNsearch - 30","113","TITAN BLACK"],"associatedColumns":["Train NLL"],"associatedMergedColumns":[]},{"number":"40.7","isBolded":false,"associatedRows":["RNNsearch - 50","111","Quadro K - 6000"],"associatedColumns":["Train NLL"],"associatedMergedColumns":[]},{"number":"6.67","isBolded":false,"associatedRows":["RNNsearch - 50"],"associatedColumns":["Updates ( ?10"],"associatedMergedColumns":[]},{"number":"3.6","isBolded":false,"associatedRows":["RNNsearch - 30"],"associatedColumns":["Epochs"],"associatedMergedColumns":[]},{"number":"8.46","isBolded":false,"associatedRows":["RNNenc - 30"],"associatedColumns":["Updates ( ?10"],"associatedMergedColumns":[]}]}]