[{"caption":"Method \n\nTraining Config. \nTest Config. Classification \n(Accuracy) \n\nRetrieval \n(mAP) \nPre-train \nFine-tune #Views \n#Views \n\n(1) SPH [16] \n-\n-\n-\n-\n68.2% \n33.3% \n(2) LFD [5] \n-\n-\n-\n-\n75.5% \n40.9% \n(3) 3D ShapeNets [37] \nModelNet40 ModelNet40 \n-\n-\n77.3% \n49.2% \n\n(4) FV \n-\nModelNet40 \n12 \n1 \n78.8% \n37.5% \n(5) FV, 12? \n-\nModelNet40 \n12 \n12 \n84.8% \n43.9% \n(6) CNN \nImageNet1K \n-\n-\n1 \n83.0% \n44.1% \n(7) CNN, f.t. \nImageNet1K ModelNet40 \n12 \n1 \n85.1% \n61.7% \n(8) CNN, 12? \nImageNet1K \n-\n-\n12 \n87.5% \n49.6% \n(9) CNN, f.t.,12? \nImageNet1K ModelNet40 \n12 \n12 \n88.6% \n62.8% \n\n(10) MVCNN, 12? \nImageNet1K \n-\n-\n12 \n88.1% \n49.4% \n(11) MVCNN, f.t., 12? \nImageNet1K ModelNet40 \n12 \n12 \n89.9% \n70.1% \n(12) MVCNN, f.t.+metric, 12? ImageNet1K ModelNet40 \n12 \n12 \n89.5% \n80.2% \n(13) MVCNN, 80? \nImageNet1K \n-\n80 \n80 \n84.3% \n36.8% \n(14) MVCNN, f.t., 80? \nImageNet1K ModelNet40 \n80 \n80 \n90.1% \n70.4% \n(15) MVCNN, f.t.+metric, 80? ImageNet1K ModelNet40 \n80 \n80 \n90.1% \n79.5% \n* f.t.\u003dfine-tuning, metric\u003dlow-rank Mahalanobis metric learning \n\nTable 1. Classification and retrieval results on the ModelNet40 dataset. On the top are results using state-of-the-art 3D shape descriptors. \nOur view-based descriptors including Fisher vectors (FV) significantly outperform these even when a single view is available at test \ntime (#Views \u003d 1). When multiple views (#Views\u003d12 or 80) are available at test time, the performance of view-based methods improve \nsignificantly. The multi-view CNN (MVCNN) architecture outperforms the view-based methods, especially for retrieval. \n\n","rows":["ImageNet1K","12","( 8 ) CNN , 12?","( 13 ) MVCNN , 80?","( 4 ) FV","ModelNet40","( 15 ) MVCNN , f . t . +metric , 80?","( 10 ) MVCNN , 12?","-","( 2 ) LFD [ 5 ]","( 9 ) CNN , f . t . , 12?","1","80","( 3 ) 3D ShapeNets [ 37 ]","( 6 ) CNN","( 14 ) MVCNN , f . t . , 80?","( 5 ) FV , 12?","( 12 ) MVCNN , f . t . +metric , 12?","( 1 ) SPH [ 16 ]","( 11 ) MVCNN , f . t . , 12?","( 7 ) CNN , f . t ."],"columns":["Retrieval","Classification","( Accuracy )","#Views","( mAP )"],"mergedAllColumns":["Method"],"numberCells":[{"number":"44.1%","isBolded":false,"associatedRows":["( 6 ) CNN","ImageNet1K","-","-","1"],"associatedColumns":["Retrieval","( mAP )","#Views"],"associatedMergedColumns":["Method"]},{"number":"89.9%","isBolded":false,"associatedRows":["( 11 ) MVCNN , f . t . , 12?","ImageNet1K","ModelNet40","12","12"],"associatedColumns":["Classification","( Accuracy )","#Views"],"associatedMergedColumns":["Method"]},{"number":"36.8%","isBolded":false,"associatedRows":["( 13 ) MVCNN , 80?","ImageNet1K","-","80","80"],"associatedColumns":["Retrieval","( mAP )","#Views"],"associatedMergedColumns":["Method"]},{"number":"68.2%","isBolded":false,"associatedRows":["( 1 ) SPH [ 16 ]","-","-","-","-"],"associatedColumns":["Classification","( Accuracy )","#Views"],"associatedMergedColumns":["Method"]},{"number":"78.8%","isBolded":false,"associatedRows":["( 4 ) FV","-","ModelNet40","12","1"],"associatedColumns":["Classification","( Accuracy )","#Views"],"associatedMergedColumns":["Method"]},{"number":"49.2%","isBolded":false,"associatedRows":["( 3 ) 3D ShapeNets [ 37 ]","ModelNet40","ModelNet40","-","-"],"associatedColumns":["Retrieval","( mAP )","#Views"],"associatedMergedColumns":["Method"]},{"number":"33.3%","isBolded":false,"associatedRows":["( 1 ) SPH [ 16 ]","-","-","-","-"],"associatedColumns":["Retrieval","( mAP )","#Views"],"associatedMergedColumns":["Method"]},{"number":"70.1%","isBolded":false,"associatedRows":["( 11 ) MVCNN , f . t . , 12?","ImageNet1K","ModelNet40","12","12"],"associatedColumns":["Retrieval","( mAP )","#Views"],"associatedMergedColumns":["Method"]},{"number":"49.4%","isBolded":false,"associatedRows":["( 10 ) MVCNN , 12?","ImageNet1K","-","-","12"],"associatedColumns":["Retrieval","( mAP )","#Views"],"associatedMergedColumns":["Method"]},{"number":"43.9%","isBolded":false,"associatedRows":["( 5 ) FV , 12?","-","ModelNet40","12","12"],"associatedColumns":["Retrieval","( mAP )","#Views"],"associatedMergedColumns":["Method"]},{"number":"88.1%","isBolded":false,"associatedRows":["( 10 ) MVCNN , 12?","ImageNet1K","-","-","12"],"associatedColumns":["Classification","( Accuracy )","#Views"],"associatedMergedColumns":["Method"]},{"number":"61.7%","isBolded":false,"associatedRows":["( 7 ) CNN , f . t .","ImageNet1K","ModelNet40","12","1"],"associatedColumns":["Retrieval","( mAP )","#Views"],"associatedMergedColumns":["Method"]},{"number":"84.8%","isBolded":false,"associatedRows":["( 5 ) FV , 12?","-","ModelNet40","12","12"],"associatedColumns":["Classification","( Accuracy )","#Views"],"associatedMergedColumns":["Method"]},{"number":"90.1%","isBolded":true,"associatedRows":["( 14 ) MVCNN , f . t . , 80?","ImageNet1K","ModelNet40","80","80"],"associatedColumns":["Classification","( Accuracy )","#Views"],"associatedMergedColumns":["Method"]},{"number":"89.5%","isBolded":false,"associatedRows":["( 12 ) MVCNN , f . t . +metric , 12?","ImageNet1K","ModelNet40","12","12"],"associatedColumns":["Classification","( Accuracy )","#Views"],"associatedMergedColumns":["Method"]},{"number":"87.5%","isBolded":false,"associatedRows":["( 8 ) CNN , 12?","ImageNet1K","-","-","12"],"associatedColumns":["Classification","( Accuracy )","#Views"],"associatedMergedColumns":["Method"]},{"number":"88.6%","isBolded":false,"associatedRows":["( 9 ) CNN , f . t . , 12?","ImageNet1K","ModelNet40","12","12"],"associatedColumns":["Classification","( Accuracy )","#Views"],"associatedMergedColumns":["Method"]},{"number":"85.1%","isBolded":false,"associatedRows":["( 7 ) CNN , f . t .","ImageNet1K","ModelNet40","12","1"],"associatedColumns":["Classification","( Accuracy )","#Views"],"associatedMergedColumns":["Method"]},{"number":"77.3%","isBolded":false,"associatedRows":["( 3 ) 3D ShapeNets [ 37 ]","ModelNet40","ModelNet40","-","-"],"associatedColumns":["Classification","( Accuracy )","#Views"],"associatedMergedColumns":["Method"]},{"number":"83.0%","isBolded":false,"associatedRows":["( 6 ) CNN","ImageNet1K","-","-","1"],"associatedColumns":["Classification","( Accuracy )","#Views"],"associatedMergedColumns":["Method"]},{"number":"75.5%","isBolded":false,"associatedRows":["( 2 ) LFD [ 5 ]","-","-","-","-"],"associatedColumns":["Classification","( Accuracy )","#Views"],"associatedMergedColumns":["Method"]},{"number":"70.4%","isBolded":false,"associatedRows":["( 14 ) MVCNN , f . t . , 80?","ImageNet1K","ModelNet40","80","80"],"associatedColumns":["Retrieval","( mAP )","#Views"],"associatedMergedColumns":["Method"]},{"number":"62.8%","isBolded":false,"associatedRows":["( 9 ) CNN , f . t . , 12?","ImageNet1K","ModelNet40","12","12"],"associatedColumns":["Retrieval","( mAP )","#Views"],"associatedMergedColumns":["Method"]},{"number":"40.9%","isBolded":false,"associatedRows":["( 2 ) LFD [ 5 ]","-","-","-","-"],"associatedColumns":["Retrieval","( mAP )","#Views"],"associatedMergedColumns":["Method"]},{"number":"90.1%","isBolded":true,"associatedRows":["( 15 ) MVCNN , f . t . +metric , 80?","ImageNet1K","ModelNet40","80","80"],"associatedColumns":["Classification","( Accuracy )","#Views"],"associatedMergedColumns":["Method"]},{"number":"80.2%","isBolded":true,"associatedRows":["( 12 ) MVCNN , f . t . +metric , 12?","ImageNet1K","ModelNet40","12","12"],"associatedColumns":["Retrieval","( mAP )","#Views"],"associatedMergedColumns":["Method"]},{"number":"79.5%","isBolded":false,"associatedRows":["( 15 ) MVCNN , f . t . +metric , 80?","ImageNet1K","ModelNet40","80","80"],"associatedColumns":["Retrieval","( mAP )","#Views"],"associatedMergedColumns":["Method"]},{"number":"49.6%","isBolded":false,"associatedRows":["( 8 ) CNN , 12?","ImageNet1K","-","-","12"],"associatedColumns":["Retrieval","( mAP )","#Views"],"associatedMergedColumns":["Method"]},{"number":"84.3%","isBolded":false,"associatedRows":["( 13 ) MVCNN , 80?","ImageNet1K","-","80","80"],"associatedColumns":["Classification","( Accuracy )","#Views"],"associatedMergedColumns":["Method"]},{"number":"37.5%","isBolded":false,"associatedRows":["( 4 ) FV","-","ModelNet40","12","1"],"associatedColumns":["Retrieval","( mAP )","#Views"],"associatedMergedColumns":["Method"]}]}]