[{"caption":"Classifier \n\nFeature set \nF 1 \n\nSVM \n\nPOS, WordNet, prefixes and other morphological features, \n82.2 \ndepdency parse, Levin classes, PropBank, FanmeNet, \nNomLex-Plus, Google n-gram, paraphrases, TextRunner \n\nRNN \nWord embeddings \n74.8 \nWord embeddings, POS, NER, WordNet \n77.6 \n\nMVRNN \nWord embeddings \n79.1 \nWord embeddings, POS, NER, WordNet \n82.4 \n\nCNN \nWord embeddings \n69.7 \nWord embeddings, word position embeddings, WordNet \n82.7 \nChain CNN Word embeddings, POS, NER, WordNet \n82.7 \n\nFCM \nWord embeddings \n80.6 \nWord embeddings, depedency parsing, NER \n83.0 \n\nCR-CNN \n\nWord embeddings \n82.8  ? \nWord embeddings, position embeddings \n82.7 \nWord embeddings, position embeddings \n84.1  ? \n\nSDP-LSTM \n\nWord embeddings \n82.4 \nWord embeddings, POS embeddings, WordNet embeddings, \n83.7 \ngrammar relation embeddings \n\nTable 1: Comparison of relation classification systems. The \" ?\" remark refers to special treatment for \nthe Other class. \n\n","rows":["Word embeddings , word position embeddings , WordNet","Word embeddings , position embeddings","depdency parse , Levin classes , PropBank , FanmeNet ,","Word embeddings , depedency parsing , NER","Word embeddings , POS , NER , WordNet","SVM","CR - CNN","Chain CNN","Word embeddings"],"columns":["1","F"],"mergedAllColumns":["FCM","CNN","RNN","NomLex - Plus , Google n - gram , paraphrases , TextRunner","POS , WordNet , prefixes and other morphological features ,","MVRNN"],"numberCells":[{"number":"69.7","isBolded":false,"associatedRows":["Chain CNN","Word embeddings"],"associatedColumns":["F","1"],"associatedMergedColumns":["MVRNN"]},{"number":"83.0","isBolded":false,"associatedRows":["Chain CNN","Word embeddings , depedency parsing , NER"],"associatedColumns":["F","1"],"associatedMergedColumns":["CNN"]},{"number":"82.7","isBolded":false,"associatedRows":["Chain CNN","Word embeddings , POS , NER , WordNet"],"associatedColumns":["F","1"],"associatedMergedColumns":["CNN"]},{"number":"82.4","isBolded":false,"associatedRows":["Chain CNN","Word embeddings , POS , NER , WordNet"],"associatedColumns":["F","1"],"associatedMergedColumns":["RNN"]},{"number":"80.6","isBolded":false,"associatedRows":["Chain CNN","Word embeddings"],"associatedColumns":["F","1"],"associatedMergedColumns":["CNN"]},{"number":"82.2","isBolded":false,"associatedRows":["SVM","depdency parse , Levin classes , PropBank , FanmeNet ,"],"associatedColumns":["F","1"],"associatedMergedColumns":["POS , WordNet , prefixes and other morphological features ,"]},{"number":"79.1","isBolded":false,"associatedRows":["Chain CNN","Word embeddings"],"associatedColumns":["F","1"],"associatedMergedColumns":["RNN"]},{"number":"84.1?","isBolded":true,"associatedRows":["CR - CNN","Word embeddings , position embeddings"],"associatedColumns":["F","1"],"associatedMergedColumns":["FCM"]},{"number":"82.4","isBolded":false,"associatedRows":["CR - CNN","Word embeddings"],"associatedColumns":["F","1"],"associatedMergedColumns":["FCM"]},{"number":"82.8?","isBolded":false,"associatedRows":["Chain CNN","Word embeddings"],"associatedColumns":["F","1"],"associatedMergedColumns":["FCM"]},{"number":"74.8","isBolded":false,"associatedRows":["Chain CNN","Word embeddings"],"associatedColumns":["F","1"],"associatedMergedColumns":["NomLex - Plus , Google n - gram , paraphrases , TextRunner"]},{"number":"83.7","isBolded":true,"associatedRows":["CR - CNN","Word embeddings , position embeddings"],"associatedColumns":["F","1"],"associatedMergedColumns":["FCM"]},{"number":"82.7","isBolded":false,"associatedRows":["CR - CNN","Word embeddings , position embeddings"],"associatedColumns":["F","1"],"associatedMergedColumns":["FCM"]},{"number":"77.6","isBolded":false,"associatedRows":["Chain CNN","Word embeddings , POS , NER , WordNet"],"associatedColumns":["F","1"],"associatedMergedColumns":["NomLex - Plus , Google n - gram , paraphrases , TextRunner"]},{"number":"82.7","isBolded":false,"associatedRows":["Chain CNN","Word embeddings , word position embeddings , WordNet"],"associatedColumns":["F","1"],"associatedMergedColumns":["MVRNN"]}]},{"caption":"Table 2: Effect of different channels. \n\n","rows":["+ POS embeddings ( only )","+ GR embeddings ( only )","+ POS + GR + WordNet embeddings","Word embeddings","+ WordNet embeddings ( only )"],"columns":["F"],"mergedAllColumns":["1"],"numberCells":[{"number":"82.98","isBolded":false,"associatedRows":["+ POS embeddings ( only )"],"associatedColumns":["F"],"associatedMergedColumns":["1"]},{"number":"82.35","isBolded":false,"associatedRows":["Word embeddings","+ POS + GR + WordNet embeddings"],"associatedColumns":["F"],"associatedMergedColumns":["1"]},{"number":"83.21","isBolded":false,"associatedRows":["+ GR embeddings ( only )"],"associatedColumns":["F"],"associatedMergedColumns":["1"]},{"number":"83.03","isBolded":false,"associatedRows":["+ WordNet embeddings ( only )"],"associatedColumns":["F"],"associatedMergedColumns":["1"]},{"number":"83.70","isBolded":false,"associatedRows":["+ POS + GR + WordNet embeddings"],"associatedColumns":["F"],"associatedMergedColumns":["1"]}]}]