[{"caption":"Table 1: Distances in image space \n\nRow/Method CycleGAN UGAN UGAN-P \nA \n116.45 \n85.71 \n86.15 \nB \n114.49 \n97.92 \n101.01 \nC \n120.84 \n96.53 \n97.57 \nD \n129.27 \n108.90 \n110.50 \nMean \n111.60 \n94.91 \n96.51 \n\n","rows":["A","Mean","B","C","D"],"columns":["Table 1 : Distances in image space","UGAN","CycleGAN","UGAN - P"],"mergedAllColumns":[],"numberCells":[{"number":"96.51","isBolded":false,"associatedRows":["Mean"],"associatedColumns":["Table 1 : Distances in image space","UGAN - P"],"associatedMergedColumns":[]},{"number":"97.57","isBolded":false,"associatedRows":["C"],"associatedColumns":["Table 1 : Distances in image space","UGAN - P"],"associatedMergedColumns":[]},{"number":"108.90","isBolded":false,"associatedRows":["D"],"associatedColumns":["Table 1 : Distances in image space","UGAN"],"associatedMergedColumns":[]},{"number":"120.84","isBolded":false,"associatedRows":["C"],"associatedColumns":["Table 1 : Distances in image space","CycleGAN"],"associatedMergedColumns":[]},{"number":"86.15","isBolded":false,"associatedRows":["A"],"associatedColumns":["Table 1 : Distances in image space","UGAN - P"],"associatedMergedColumns":[]},{"number":"129.27","isBolded":false,"associatedRows":["D"],"associatedColumns":["Table 1 : Distances in image space","CycleGAN"],"associatedMergedColumns":[]},{"number":"101.01","isBolded":false,"associatedRows":["B"],"associatedColumns":["Table 1 : Distances in image space","UGAN - P"],"associatedMergedColumns":[]},{"number":"96.53","isBolded":false,"associatedRows":["C"],"associatedColumns":["Table 1 : Distances in image space","UGAN"],"associatedMergedColumns":[]},{"number":"97.92","isBolded":false,"associatedRows":["B"],"associatedColumns":["Table 1 : Distances in image space","UGAN"],"associatedMergedColumns":[]},{"number":"111.60","isBolded":false,"associatedRows":["Mean"],"associatedColumns":["Table 1 : Distances in image space","CycleGAN"],"associatedMergedColumns":[]},{"number":"85.71","isBolded":false,"associatedRows":["A"],"associatedColumns":["Table 1 : Distances in image space","UGAN"],"associatedMergedColumns":[]},{"number":"110.50","isBolded":false,"associatedRows":["D"],"associatedColumns":["Table 1 : Distances in image space","UGAN - P"],"associatedMergedColumns":[]},{"number":"116.45","isBolded":false,"associatedRows":["A"],"associatedColumns":["Table 1 : Distances in image space","CycleGAN"],"associatedMergedColumns":[]},{"number":"114.49","isBolded":false,"associatedRows":["B"],"associatedColumns":["Table 1 : Distances in image space","CycleGAN"],"associatedMergedColumns":[]},{"number":"94.91","isBolded":false,"associatedRows":["Mean"],"associatedColumns":["Table 1 : Distances in image space","UGAN"],"associatedMergedColumns":[]}]},{"caption":"Table 2: Gradient Difference Loss Metrics \n\nMethod/Patch CycleGAN UGAN UGAN-P \nRed \n11.53 \n9.39 \n10.93 \nBlue \n7.52 \n4.83 \n5.50 \nGreen \n4.15 \n3.18 \n3.25 \nOrange \n6.72 \n5.65 \n5.79 \n\n4.4 Diver Tracking using Frequency-\nDomain Detection \n\nWe investigate the frequency-domain character-\nistics of the restored images through a case-study \nof periodic motion tracking in sequence of im-\nages. Particularly, we compared the performance \nof Mixed Domain Periodic Motion (MDPM)-\ntracker [13] on a sequence of images of a \ndiver swimming in arbitrary directions. MDPM \ntracker is designed for underwater robots to fol-\nlow scuba divers by tracking distinct frequency-\ndomain signatures (high-amplitude spectra at 1-\n2Hz) pertaining to human swimming. Ampli-\ntude spectra in frequency-domain correspond to \nthe periodic intensity variations in image-space \nover time, which is often eroded in noisy under-\nwater images [27]. \n\n","rows":["Red","Blue","Orange","Green"],"columns":["Method / Patch","UGAN","Table 2 : Gradient Difference Loss Metrics","CycleGAN","UGAN - P"],"mergedAllColumns":[],"numberCells":[{"number":"6.72","isBolded":false,"associatedRows":["Orange"],"associatedColumns":["Table 2 : Gradient Difference Loss Metrics","CycleGAN"],"associatedMergedColumns":[]},{"number":"4.4","isBolded":true,"associatedRows":[],"associatedColumns":["Table 2 : Gradient Difference Loss Metrics","Method / Patch"],"associatedMergedColumns":[]},{"number":"11.53","isBolded":false,"associatedRows":["Red"],"associatedColumns":["Table 2 : Gradient Difference Loss Metrics","CycleGAN"],"associatedMergedColumns":[]},{"number":"3.18","isBolded":false,"associatedRows":["Green"],"associatedColumns":["Table 2 : Gradient Difference Loss Metrics","UGAN"],"associatedMergedColumns":[]},{"number":"4.15","isBolded":false,"associatedRows":["Green"],"associatedColumns":["Table 2 : Gradient Difference Loss Metrics","CycleGAN"],"associatedMergedColumns":[]},{"number":"5.65","isBolded":false,"associatedRows":["Orange"],"associatedColumns":["Table 2 : Gradient Difference Loss Metrics","UGAN"],"associatedMergedColumns":[]},{"number":"7.52","isBolded":false,"associatedRows":["Blue"],"associatedColumns":["Table 2 : Gradient Difference Loss Metrics","CycleGAN"],"associatedMergedColumns":[]},{"number":"4.83","isBolded":false,"associatedRows":["Blue"],"associatedColumns":["Table 2 : Gradient Difference Loss Metrics","UGAN"],"associatedMergedColumns":[]},{"number":"5.50","isBolded":false,"associatedRows":["Blue"],"associatedColumns":["Table 2 : Gradient Difference Loss Metrics","UGAN - P"],"associatedMergedColumns":[]},{"number":"5.79","isBolded":false,"associatedRows":["Orange"],"associatedColumns":["Table 2 : Gradient Difference Loss Metrics","UGAN - P"],"associatedMergedColumns":[]},{"number":"3.25","isBolded":false,"associatedRows":["Green"],"associatedColumns":["Table 2 : Gradient Difference Loss Metrics","UGAN - P"],"associatedMergedColumns":[]},{"number":"9.39","isBolded":false,"associatedRows":["Red"],"associatedColumns":["Table 2 : Gradient Difference Loss Metrics","UGAN"],"associatedMergedColumns":[]},{"number":"10.93","isBolded":false,"associatedRows":["Red"],"associatedColumns":["Table 2 : Gradient Difference Loss Metrics","UGAN - P"],"associatedMergedColumns":[]}]}]