[{"caption":"Algorithm \nTraining Environment \nResources \nMedian \nMedian \nTime \nFrames \n(per game) (no-op starts) (human starts) \nApe-X DQN \n5 days \n22800M 376 cores, 1 GPU a \n434% \n358% \nRainbow \n10 days \n200M \n1 GPU \n223% \n153% \nDistributional (C51) \n10 days \n200M \n1 GPU \n178% \n125% \nA3C \n4 days \n-\n16 cores \n-\n117% \nPrioritized Dueling \n9.5 days \n200M \n1 GPU \n172% \n115% \nDQN \n9.5 days \n200M \n1 GPU \n79% \n68% \nGorila DQN c \n?4 days \n-\nunknown b \n96% \n78% \nUNREAL d \n-\n250M \n16 cores \n331% d \n250% d \n\nTable 1: Median normalized scores across 57 Atari games. a Tesla P100. b \u003e100 CPUs, with a mixed number \n\nof cores per CPU machine. c Only evaluated on 49 games. d Hyper-parameters were tuned per game. \n\n","rows":["5 days","DQN","376 cores , 1 GPU a","200M","-","4 days","Ape - X DQN","A3C","10 days","16 cores","Rainbow","Distributional ( C51 )","250M","22800M","UNREAL d","Prioritized Dueling","1 GPU"],"columns":["Training","79%","68%","78%","96%","Median","Time","( no - op starts )","( human starts )"],"mergedAllColumns":[],"numberCells":[{"number":"358%","isBolded":true,"associatedRows":["Ape - X DQN","5 days","22800M","376 cores , 1 GPU a"],"associatedColumns":["Median","( human starts )"],"associatedMergedColumns":[]},{"number":"434%","isBolded":true,"associatedRows":["Ape - X DQN","5 days","22800M","376 cores , 1 GPU a"],"associatedColumns":["Median","( no - op starts )"],"associatedMergedColumns":[]},{"number":"153%","isBolded":false,"associatedRows":["Rainbow","10 days","200M","1 GPU"],"associatedColumns":["Median","( human starts )"],"associatedMergedColumns":[]},{"number":"172%","isBolded":false,"associatedRows":["Prioritized Dueling","4 days","200M","1 GPU"],"associatedColumns":["Median","( no - op starts )"],"associatedMergedColumns":[]},{"number":"115%","isBolded":false,"associatedRows":["Prioritized Dueling","4 days","200M","1 GPU"],"associatedColumns":["Median","( human starts )"],"associatedMergedColumns":[]},{"number":"331%d","isBolded":false,"associatedRows":["UNREAL d","-","250M","16 cores"],"associatedColumns":["Median","( no - op starts )","79%","96%"],"associatedMergedColumns":[]},{"number":"117%","isBolded":false,"associatedRows":["A3C","4 days","-","16 cores","-"],"associatedColumns":["Median","( human starts )"],"associatedMergedColumns":[]},{"number":"9.5days","isBolded":false,"associatedRows":["DQN"],"associatedColumns":["Training","Time"],"associatedMergedColumns":[]},{"number":"9.5days","isBolded":false,"associatedRows":["Prioritized Dueling"],"associatedColumns":["Training","Time"],"associatedMergedColumns":[]},{"number":"178%","isBolded":false,"associatedRows":["Distributional ( C51 )","10 days","200M","1 GPU"],"associatedColumns":["Median","( no - op starts )"],"associatedMergedColumns":[]},{"number":"250%d","isBolded":false,"associatedRows":["UNREAL d","-","250M","16 cores"],"associatedColumns":["Median","( human starts )","68%","78%"],"associatedMergedColumns":[]},{"number":"223%","isBolded":false,"associatedRows":["Rainbow","10 days","200M","1 GPU"],"associatedColumns":["Median","( no - op starts )"],"associatedMergedColumns":[]},{"number":"125%","isBolded":false,"associatedRows":["Distributional ( C51 )","10 days","200M","1 GPU"],"associatedColumns":["Median","( human starts )"],"associatedMergedColumns":[]}]}]