[{"caption":"). Both the StrongNeu-\nral and BestPlan systems outperform all the \nWebNLG participating systems on all automatic \nmetrics (Table 1). BestPlan is competitive with \nStrongNeural in all metrics, with small differ-\nences either way per metric. \n\n14 \n\n12 Note that this only affects the training stage. At test time, \nwe do not require gold plans, and evaluate on all sentences. \n13 https://github.com/Maluuba/nlg-eval \n14 At least part of the stronger results for StrongNeural can \nbe attributed to its ability to generate referring expressions, \nwhich we currently do not support. \n\nBLEU METEOR ROUGE L CIDEr \nUPF-FORGe \n\n? \n\n38.5 \n0.390 \n60.9 \n2.500 \nMelbourne \n\n? \n\n45.0 \n0.376 \n63.5 \n2.814 \n\nRandomPlan-1 \n\n? \n\n43.3 \n0.384 \n57.6 \n2.342 \nRandomPlan-2 \n\n? \n\n43.5 \n0.384 \n57.4 \n2.332 \nRandomPlan-3 \n\n? \n\n43.5 \n0.384 \n57.4 \n2.303 \nStrongNeural \n\n? \n\n46.5 \n0.392 \n65.4 \n2.866 \nBestPlan \n\n? \n\n47.4 \n0.391 \n63.1 \n2.692 \n\nTable 1: Results for all categories. Team color indicates \nthe type of system used (NMT \n? , Rule-Based \n? , Rule-\n\nBased + NMT \n? ). \n\n","rows":["Melbourne ?","BestPlan ?","RandomPlan - 1","RandomPlan - 2","RandomPlan - 3","UPF - FORGe ?","StrongNeural ?"],"columns":["METEOR","BLEU","CIDEr","ROUGE"],"mergedAllColumns":["?"],"numberCells":[{"number":"43.3","isBolded":false,"associatedRows":["RandomPlan - 1"],"associatedColumns":["BLEU"],"associatedMergedColumns":[]},{"number":"43.5","isBolded":false,"associatedRows":["RandomPlan - 2"],"associatedColumns":["BLEU"],"associatedMergedColumns":["?"]},{"number":"0.376","isBolded":false,"associatedRows":["Melbourne ?"],"associatedColumns":["METEOR"],"associatedMergedColumns":[]},{"number":"0.390","isBolded":false,"associatedRows":["UPF - FORGe ?"],"associatedColumns":["METEOR"],"associatedMergedColumns":[]},{"number":"57.6","isBolded":false,"associatedRows":["RandomPlan - 1"],"associatedColumns":["ROUGE"],"associatedMergedColumns":[]},{"number":"0.391","isBolded":false,"associatedRows":["BestPlan ?"],"associatedColumns":["METEOR"],"associatedMergedColumns":["?"]},{"number":"2.332","isBolded":false,"associatedRows":["RandomPlan - 2"],"associatedColumns":["CIDEr"],"associatedMergedColumns":["?"]},{"number":"65.4","isBolded":true,"associatedRows":["StrongNeural ?"],"associatedColumns":["ROUGE"],"associatedMergedColumns":["?"]},{"number":"2.692","isBolded":false,"associatedRows":["BestPlan ?"],"associatedColumns":["CIDEr"],"associatedMergedColumns":["?"]},{"number":"38.5","isBolded":false,"associatedRows":["UPF - FORGe ?"],"associatedColumns":["BLEU"],"associatedMergedColumns":[]},{"number":"60.9","isBolded":false,"associatedRows":["UPF - FORGe ?"],"associatedColumns":["ROUGE"],"associatedMergedColumns":[]},{"number":"0.384","isBolded":false,"associatedRows":["RandomPlan - 2"],"associatedColumns":["METEOR"],"associatedMergedColumns":["?"]},{"number":"45.0","isBolded":false,"associatedRows":["Melbourne ?"],"associatedColumns":["BLEU"],"associatedMergedColumns":[]},{"number":"2.342","isBolded":false,"associatedRows":["RandomPlan - 1"],"associatedColumns":["CIDEr"],"associatedMergedColumns":[]},{"number":"2.303","isBolded":false,"associatedRows":["RandomPlan - 3"],"associatedColumns":["CIDEr"],"associatedMergedColumns":["?"]},{"number":"46.5","isBolded":false,"associatedRows":["StrongNeural ?"],"associatedColumns":["BLEU"],"associatedMergedColumns":["?"]},{"number":"57.4","isBolded":false,"associatedRows":["RandomPlan - 2"],"associatedColumns":["ROUGE"],"associatedMergedColumns":["?"]},{"number":"57.4","isBolded":false,"associatedRows":["RandomPlan - 3"],"associatedColumns":["ROUGE"],"associatedMergedColumns":["?"]},{"number":"63.5","isBolded":false,"associatedRows":["Melbourne ?"],"associatedColumns":["ROUGE"],"associatedMergedColumns":[]},{"number":"0.392","isBolded":true,"associatedRows":["StrongNeural ?"],"associatedColumns":["METEOR"],"associatedMergedColumns":["?"]},{"number":"63.1","isBolded":false,"associatedRows":["BestPlan ?"],"associatedColumns":["ROUGE"],"associatedMergedColumns":["?"]},{"number":"2.866","isBolded":true,"associatedRows":["StrongNeural ?"],"associatedColumns":["CIDEr"],"associatedMergedColumns":["?"]},{"number":"47.4","isBolded":true,"associatedRows":["BestPlan ?"],"associatedColumns":["BLEU"],"associatedMergedColumns":["?"]},{"number":"2.814","isBolded":false,"associatedRows":["Melbourne ?"],"associatedColumns":["CIDEr"],"associatedMergedColumns":[]},{"number":"0.384","isBolded":false,"associatedRows":["RandomPlan - 1"],"associatedColumns":["METEOR"],"associatedMergedColumns":[]},{"number":"0.384","isBolded":false,"associatedRows":["RandomPlan - 3"],"associatedColumns":["METEOR"],"associatedMergedColumns":["?"]},{"number":"43.5","isBolded":false,"associatedRows":["RandomPlan - 3"],"associatedColumns":["BLEU"],"associatedMergedColumns":["?"]},{"number":"2.500","isBolded":false,"associatedRows":["UPF - FORGe ?"],"associatedColumns":["CIDEr"],"associatedMergedColumns":[]}]},{"caption":"Table 4: Surface realizer performance. Entities: Per-\ncent of sentence plans that were realized with all the \nrequested entities. Order: of the sentences that were \nrealized with all requested entities, percentage of real-\nizations that followed the requested entity order. \n\ntency we defined above, do all entities appear in \nthe same order in the plan and the realization. \n","rows":["100%","Unseen","Seen"],"columns":["Order","Top 1% Plans","Best Plan","Top 10% Plans","Entities"],"mergedAllColumns":["100%"],"numberCells":[{"number":"93.6%","isBolded":false,"associatedRows":["Seen","100%"],"associatedColumns":["Top 10% Plans","Entities"],"associatedMergedColumns":[]},{"number":"45.3%","isBolded":false,"associatedRows":["Unseen","100%"],"associatedColumns":["Top 1% Plans","Entities"],"associatedMergedColumns":["100%"]},{"number":"98.9%","isBolded":false,"associatedRows":["Seen"],"associatedColumns":["Best Plan","Entities"],"associatedMergedColumns":[]},{"number":"66.7%","isBolded":false,"associatedRows":["Unseen"],"associatedColumns":["Best Plan","Entities"],"associatedMergedColumns":["100%"]},{"number":"95.9%","isBolded":false,"associatedRows":["Seen","100%"],"associatedColumns":["Top 1% Plans","Entities"],"associatedMergedColumns":[]},{"number":"99.9%","isBolded":false,"associatedRows":["Seen","100%"],"associatedColumns":["Top 1% Plans","Order"],"associatedMergedColumns":[]},{"number":"41.3%","isBolded":false,"associatedRows":["Unseen","100%","100%"],"associatedColumns":["Top 10% Plans","Entities"],"associatedMergedColumns":["100%"]}]}]