[{"caption":"Table 1. Error rates on MNIST classification \n\nMethod \nError rate \n\nMNIST \nConv. GP (25-dim)  ? \n2.1% \nRBF GP (784-dim)  ? \n1.9% \nGCGP (24-dim) \n1.7% \n\nMNIST Superpixel 75 \nChebNet (Defferrard et al., 2016) \n24.4% \nMoNet (Monti et al., 2017) \n8.9% \nGCGP \n4.2% \n\n ? (van der Wilk et al., 2017) \n\ninput dimensions, attains a 1.9% error rate (van der Wilk \net al., 2017). It is important to note that both the convolu-\ntional GP and our GCGP are not hierarchical models, and \nto increase expressibility, van der Wilk et al. (2017) include \nlearnable weights which multiply the patch response func-\ntion for each patch. This increases classification accuracy \nbut means that it is no longer strictly translation-invariant. \nOur GCGP model can similarly be extended, but this is left \nfor future work. The hyperparameters ? k and ? ? converge \nto {1.312, 2.331, 4.034} and 0.392. \n\n","rows":["ChebNet ( Defferrard et al . , 2016 )","GCGP","GCGP ( 24 - dim )","input dimensions , attains a","to {1 . 312 ,","MoNet ( Monti et al . , 2017 )"],"columns":["Table 1 . Error rates on MNIST classification","Error rate","Method"],"mergedAllColumns":["? converge","MNIST Superpixel 75","MNIST","? ( van der Wilk et al . , 2017 )"],"numberCells":[{"number":"8.9%","isBolded":false,"associatedRows":["MoNet ( Monti et al . , 2017 )"],"associatedColumns":["Table 1 . Error rates on MNIST classification","Error rate"],"associatedMergedColumns":["MNIST Superpixel 75"]},{"number":"1.7%","isBolded":true,"associatedRows":["GCGP ( 24 - dim )"],"associatedColumns":["Table 1 . Error rates on MNIST classification","Error rate"],"associatedMergedColumns":["MNIST"]},{"number":"4.2%","isBolded":true,"associatedRows":["GCGP"],"associatedColumns":["Table 1 . Error rates on MNIST classification","Error rate"],"associatedMergedColumns":["MNIST Superpixel 75"]},{"number":"2.331,","isBolded":false,"associatedRows":["to {1 . 312 ,"],"associatedColumns":["Table 1 . Error rates on MNIST classification","Method"],"associatedMergedColumns":["? converge"]},{"number":"2.1%","isBolded":false,"associatedRows":["ChebNet ( Defferrard et al . , 2016 )"],"associatedColumns":["Table 1 . Error rates on MNIST classification","Error rate"],"associatedMergedColumns":["MNIST"]},{"number":"4.034}and","isBolded":false,"associatedRows":["to {1 . 312 ,","GCGP"],"associatedColumns":["Table 1 . Error rates on MNIST classification","Method"],"associatedMergedColumns":["? converge"]},{"number":"0.392.","isBolded":false,"associatedRows":["input dimensions , attains a"],"associatedColumns":["Table 1 . Error rates on MNIST classification","Error rate"],"associatedMergedColumns":["? converge"]},{"number":"1.9%errorrate(vanderWilk","isBolded":false,"associatedRows":["input dimensions , attains a"],"associatedColumns":["Table 1 . Error rates on MNIST classification","Error rate"],"associatedMergedColumns":["? ( van der Wilk et al . , 2017 )"]},{"number":"24.4%","isBolded":false,"associatedRows":["ChebNet ( Defferrard et al . , 2016 )"],"associatedColumns":["Table 1 . Error rates on MNIST classification","Error rate"],"associatedMergedColumns":["MNIST Superpixel 75"]},{"number":"1.9%","isBolded":false,"associatedRows":["ChebNet ( Defferrard et al . , 2016 )"],"associatedColumns":["Table 1 . Error rates on MNIST classification","Error rate"],"associatedMergedColumns":["MNIST"]}]},{"caption":"Table 2. Ablation study on Superpixel 75 error rates \n\nExamples per class \n100 \n500 \n1000 \n\nError rate \n13.7% 8.3% 6.3% \n\n","rows":["Error rate"],"columns":["100","Table 2 . Ablation study on Superpixel 75 error rates","500","1000"],"mergedAllColumns":[],"numberCells":[{"number":"13.7%","isBolded":false,"associatedRows":["Error rate"],"associatedColumns":["Table 2 . Ablation study on Superpixel 75 error rates","100"],"associatedMergedColumns":[]},{"number":"6.3%","isBolded":false,"associatedRows":["Error rate"],"associatedColumns":["Table 2 . Ablation study on Superpixel 75 error rates","1000"],"associatedMergedColumns":[]},{"number":"8.3%","isBolded":false,"associatedRows":["Error rate"],"associatedColumns":["Table 2 . Ablation study on Superpixel 75 error rates","500"],"associatedMergedColumns":[]}]},{"caption":"Table 3. Error rates on MPI Faust mesh classification \n\nNumber of vertices \n500 \n1000 \n2500 \n\nMoNet \n40.00% 33.33% 33.33% \nGCGP \n23.33% 10.00% 3.33% \n\n","rows":["GCGP","MoNet"],"columns":["2500","500","1000","Table 3 . Error rates on MPI Faust mesh classification"],"mergedAllColumns":[],"numberCells":[{"number":"33.33%","isBolded":false,"associatedRows":["MoNet"],"associatedColumns":["Table 3 . Error rates on MPI Faust mesh classification","1000"],"associatedMergedColumns":[]},{"number":"3.33%","isBolded":true,"associatedRows":["GCGP"],"associatedColumns":["Table 3 . Error rates on MPI Faust mesh classification","2500"],"associatedMergedColumns":[]},{"number":"23.33%","isBolded":true,"associatedRows":["GCGP"],"associatedColumns":["Table 3 . Error rates on MPI Faust mesh classification","500"],"associatedMergedColumns":[]},{"number":"10.00%","isBolded":true,"associatedRows":["GCGP"],"associatedColumns":["Table 3 . Error rates on MPI Faust mesh classification","1000"],"associatedMergedColumns":[]},{"number":"40.00%","isBolded":false,"associatedRows":["MoNet"],"associatedColumns":["Table 3 . Error rates on MPI Faust mesh classification","500"],"associatedMergedColumns":[]},{"number":"33.33%","isBolded":false,"associatedRows":["MoNet"],"associatedColumns":["Table 3 . Error rates on MPI Faust mesh classification","2500"],"associatedMergedColumns":[]}]}]