[{"caption":"Model \nTrain \nTest \n\nConvNet \n72.6% 0.04% \nConvNetMask 91.4% 15.1% \nSATNet (ours) 99.8% 98.3% \n\n(a) Original Sudoku. \n\nModel \nTrain \nTest \n\nConvNet \n0% \n0% \nConvNetMask 0.01% \n0% \nSATNet (ours) 99.7% 98.3% \n\n(b) Permuted Sudoku. \n\nModel \nTrain \nTest \n\nConvNet \n0.31% \n0% \nConvNetMask \n89% \n0.1% \nSATNet (ours) 93.6% 63.2% \n\n(c) Visual Sudoku. (Note: the theoretical \n\"best\" test accuracy for our architecture is \n74.7%.) \n\nTable 1. Results for 9 ? 9 Sudoku experiments with 9K train/1K test examples. We compare our SATNet model against a vanilla convolu-\ntional neural network (ConvNet) as well as one that receives a binary mask indicating which bits need to be learned (ConvNetMask). \n\n","rows":["89%","0%","ConvNet","SATNet ( ours )","ConvNetMask"],"columns":["Test","Train"],"mergedAllColumns":["0%"],"numberCells":[{"number":"0.04%","isBolded":false,"associatedRows":["ConvNet"],"associatedColumns":["Test"],"associatedMergedColumns":[]},{"number":"15.1%","isBolded":false,"associatedRows":["ConvNetMask"],"associatedColumns":["Test"],"associatedMergedColumns":["0%"]},{"number":"98.3%","isBolded":true,"associatedRows":["SATNet ( ours )"],"associatedColumns":["Test"],"associatedMergedColumns":["0%"]},{"number":"0.1%","isBolded":false,"associatedRows":["ConvNetMask","ConvNetMask","0%","ConvNetMask","89%"],"associatedColumns":["Test"],"associatedMergedColumns":["0%"]},{"number":"63.2%","isBolded":true,"associatedRows":["SATNet ( ours )","SATNet ( ours )","0%","SATNet ( ours )"],"associatedColumns":["Test"],"associatedMergedColumns":["0%"]},{"number":"99.7%","isBolded":false,"associatedRows":["SATNet ( ours )","SATNet ( ours )"],"associatedColumns":["Train"],"associatedMergedColumns":["0%"]},{"number":"99.8%","isBolded":false,"associatedRows":["SATNet ( ours )"],"associatedColumns":["Train"],"associatedMergedColumns":["0%"]},{"number":"72.6%","isBolded":false,"associatedRows":["ConvNet"],"associatedColumns":["Train"],"associatedMergedColumns":[]},{"number":"0.31%","isBolded":false,"associatedRows":["ConvNet","ConvNet","0%","0%","ConvNet"],"associatedColumns":["Train"],"associatedMergedColumns":[]},{"number":"91.4%","isBolded":false,"associatedRows":["ConvNetMask"],"associatedColumns":["Train"],"associatedMergedColumns":["0%"]},{"number":"98.3%","isBolded":true,"associatedRows":["SATNet ( ours )","SATNet ( ours )"],"associatedColumns":["Test"],"associatedMergedColumns":["0%"]},{"number":"0.01%","isBolded":false,"associatedRows":["ConvNetMask","ConvNetMask"],"associatedColumns":["Train"],"associatedMergedColumns":["0%"]},{"number":"93.6%","isBolded":false,"associatedRows":["SATNet ( ours )","SATNet ( ours )","0%","SATNet ( ours )"],"associatedColumns":["Train"],"associatedMergedColumns":["0%"]}]}]