[{"caption":"Table 1: Performances of NLP models \n\nTask \nModel \nDataset \nMetric \nDELTA Baseline Reference \nSequence classification \nSentences \nCNN \nTREC a \nAcc \n92.2 \n91.2 \nKim (2014) \nDocuments \nHAN \nYahoo Answer b \nAcc \n75.1 \n75.8 \nYang et al. (2016) \n\nSequence labeling \nNER \nBLSTM-CRF CoNLL2003 c \nF1 \n84.6 \n84.7 \nHuang et al. (2015) \n\nMultitask \nIntent \nBLSTM-CRF ATIS d \nAcc \n97.4 \n98.2 \nLiu and Lane (2016) \nSlot filling \nF1 \n95.2 \n95.9 \n\nPairwise modeling \nNLI \nLSTM \nSNLI e \nAcc \n80.7 \n80.6 \nBowman et al. (2016) \n\nSeq2seq \nSummarization BLSTM \nCNN/Daily Mail f RougeL 27.3 \n28.1 g \nSee et al. (2017) \n\nPretrained model \nNER \nELMO \nCoNLL2003 \nF1 \n92.2 \n92.2 \nPeters et al. (2018) \nNER \nBERT \nCoNLL2003 \nF1 \n94.6 \n94.9 \nDevlin et al. (2019) \n\na https://trec.nist.gov/data.html \nb https://webscope.sandbox.yahoo.com/#datasets \nc https://www.clips.uantwerpen.be/conll2003/ner/ \nd https://catalog.ldc.upenn.edu/docs/LDC93S4B/corpus.html \ne https://nlp.stanford.edu/projects/snli/ \nf https://github.com/deepmind/rc-data \ng Our model is slightly different from that of the reference, so a small performance gap is expected. \n\n","rows":["Acc","CNN","LSTM","TREC a","BLSTM","ELMO","CoNLL2003 c","Intent","NLI","F1","CoNLL2003","ATIS d","SNLI e","Yahoo Answer b","CNN / Daily Mail f","HAN","RougeL","Documents","Sentences","NER","BERT","BLSTM - CRF","Slot filling","Summarization"],"columns":["Table 1 : Performances of NLP models","DELTA","Baseline"],"mergedAllColumns":["Multitask","Sequence labeling","Liu and Lane ( 2016 )","Seq2seq","Pairwise modeling","Pretrained model","Peters et al . ( 2018 )","Sequence classification","Kim ( 2014 )"],"numberCells":[{"number":"95.9","isBolded":false,"associatedRows":["Slot filling","BLSTM - CRF","CNN / Daily Mail f","F1"],"associatedColumns":["Table 1 : Performances of NLP models","Baseline"],"associatedMergedColumns":["Liu and Lane ( 2016 )"]},{"number":"80.6","isBolded":false,"associatedRows":["NLI","LSTM","SNLI e","Acc"],"associatedColumns":["Table 1 : Performances of NLP models","Baseline"],"associatedMergedColumns":["Pairwise modeling"]},{"number":"27.3","isBolded":false,"associatedRows":["Summarization","BLSTM","CNN / Daily Mail f","RougeL"],"associatedColumns":["Table 1 : Performances of NLP models","DELTA"],"associatedMergedColumns":["Seq2seq"]},{"number":"75.1","isBolded":false,"associatedRows":["Documents","HAN","Yahoo Answer b","Acc"],"associatedColumns":["Table 1 : Performances of NLP models","DELTA"],"associatedMergedColumns":["Kim ( 2014 )"]},{"number":"75.8","isBolded":false,"associatedRows":["Documents","HAN","Yahoo Answer b","Acc"],"associatedColumns":["Table 1 : Performances of NLP models","Baseline"],"associatedMergedColumns":["Kim ( 2014 )"]},{"number":"95.2","isBolded":false,"associatedRows":["Slot filling","BLSTM - CRF","CNN / Daily Mail f","F1"],"associatedColumns":["Table 1 : Performances of NLP models","DELTA"],"associatedMergedColumns":["Liu and Lane ( 2016 )"]},{"number":"98.2","isBolded":false,"associatedRows":["Intent","BLSTM - CRF","ATIS d","Acc"],"associatedColumns":["Table 1 : Performances of NLP models","Baseline"],"associatedMergedColumns":["Multitask"]},{"number":"80.7","isBolded":false,"associatedRows":["NLI","LSTM","SNLI e","Acc"],"associatedColumns":["Table 1 : Performances of NLP models","DELTA"],"associatedMergedColumns":["Pairwise modeling"]},{"number":"94.9","isBolded":false,"associatedRows":["NER","BERT","CoNLL2003","F1"],"associatedColumns":["Table 1 : Performances of NLP models","Baseline"],"associatedMergedColumns":["Peters et al . ( 2018 )"]},{"number":"28.1g","isBolded":false,"associatedRows":["Summarization","BLSTM","CNN / Daily Mail f","RougeL"],"associatedColumns":["Table 1 : Performances of NLP models","Baseline"],"associatedMergedColumns":["Seq2seq"]},{"number":"94.6","isBolded":false,"associatedRows":["NER","BERT","CoNLL2003","F1"],"associatedColumns":["Table 1 : Performances of NLP models","DELTA"],"associatedMergedColumns":["Peters et al . ( 2018 )"]},{"number":"97.4","isBolded":false,"associatedRows":["Intent","BLSTM - CRF","ATIS d","Acc"],"associatedColumns":["Table 1 : Performances of NLP models","DELTA"],"associatedMergedColumns":["Multitask"]},{"number":"92.2","isBolded":false,"associatedRows":["NER","ELMO","CoNLL2003","F1"],"associatedColumns":["Table 1 : Performances of NLP models","DELTA"],"associatedMergedColumns":["Pretrained model"]},{"number":"84.7","isBolded":false,"associatedRows":["NER","BLSTM - CRF","CoNLL2003 c","F1"],"associatedColumns":["Table 1 : Performances of NLP models","Baseline"],"associatedMergedColumns":["Sequence labeling"]},{"number":"92.2","isBolded":false,"associatedRows":["Sentences","CNN","TREC a","Acc"],"associatedColumns":["Table 1 : Performances of NLP models","DELTA"],"associatedMergedColumns":["Sequence classification"]},{"number":"91.2","isBolded":false,"associatedRows":["Sentences","CNN","TREC a","Acc"],"associatedColumns":["Table 1 : Performances of NLP models","Baseline"],"associatedMergedColumns":["Sequence classification"]},{"number":"92.2","isBolded":false,"associatedRows":["NER","ELMO","CoNLL2003","F1"],"associatedColumns":["Table 1 : Performances of NLP models","Baseline"],"associatedMergedColumns":["Pretrained model"]},{"number":"84.6","isBolded":false,"associatedRows":["NER","BLSTM - CRF","CoNLL2003 c","F1"],"associatedColumns":["Table 1 : Performances of NLP models","DELTA"],"associatedMergedColumns":["Sequence labeling"]}]}]