[{"caption":"HFO \nReturn \nP(Goal) \nP(Goal) \nMP-DQN \n0.987 \n? 0.039 \n\n0.789 \n? 0.070 \n\n0.913 \n? 0.070 \nMP-DQN (no MC) -\n-\n0.509 \n? 0.110 \nHybrid SAC \n0.981 \n? 0.013 \n\n0.728 \n? 0.047 \n\n0.639 \n? 0.141 \n\nTable 1: Comparison between the Multi-Pass Deep Q-\nNetwork (MP-DQN) algorithm from (Bester, James, and \nKonidaris 2019) and our Hybrid SAC implementation. Mean \nperformance with 95% confidence interval is computed over \n30 seeds. Since the MP-DQN results on HFO take advantage \nof Monte-Carlo returns, while our Hybrid SAC does not, we \nalso report in the second row the (significantly degraded) \nperformance of MP-DQN without Monte-Carlo returns. \n\n","rows":["MP - DQN","?","MP - DQN ( no MC )","Hybrid SAC","-"],"columns":["HFO","Return","P ( Goal )"],"mergedAllColumns":[],"numberCells":[{"number":"0.141","isBolded":false,"associatedRows":["MP - DQN ( no MC )","?","?","?"],"associatedColumns":["HFO","P ( Goal )"],"associatedMergedColumns":[]},{"number":"0.039","isBolded":false,"associatedRows":["MP - DQN ( no MC )","?"],"associatedColumns":["HFO","Return"],"associatedMergedColumns":[]},{"number":"0.728","isBolded":false,"associatedRows":["Hybrid SAC","?"],"associatedColumns":["HFO","P ( Goal )"],"associatedMergedColumns":[]},{"number":"0.981","isBolded":false,"associatedRows":["Hybrid SAC"],"associatedColumns":["HFO","Return"],"associatedMergedColumns":[]},{"number":"0.047","isBolded":false,"associatedRows":["MP - DQN ( no MC )","?","?"],"associatedColumns":["HFO","P ( Goal )"],"associatedMergedColumns":[]},{"number":"0.987","isBolded":false,"associatedRows":["MP - DQN"],"associatedColumns":["HFO","Return"],"associatedMergedColumns":[]},{"number":"0.110","isBolded":false,"associatedRows":["MP - DQN ( no MC )","?","?","?"],"associatedColumns":["HFO","P ( Goal )"],"associatedMergedColumns":[]},{"number":"0.509","isBolded":false,"associatedRows":["MP - DQN ( no MC )","-","-"],"associatedColumns":["HFO","P ( Goal )"],"associatedMergedColumns":[]},{"number":"0.639","isBolded":false,"associatedRows":["Hybrid SAC","?","?"],"associatedColumns":["HFO","P ( Goal )"],"associatedMergedColumns":[]},{"number":"0.789","isBolded":false,"associatedRows":["MP - DQN","?"],"associatedColumns":["HFO","P ( Goal )"],"associatedMergedColumns":[]},{"number":"0.913","isBolded":false,"associatedRows":["MP - DQN","?","?"],"associatedColumns":["HFO","P ( Goal )"],"associatedMergedColumns":[]},{"number":"0.070","isBolded":false,"associatedRows":["MP - DQN ( no MC )","?","?","?"],"associatedColumns":["HFO","P ( Goal )"],"associatedMergedColumns":[]},{"number":"0.070","isBolded":false,"associatedRows":["MP - DQN ( no MC )","?","?"],"associatedColumns":["HFO","P ( Goal )"],"associatedMergedColumns":[]},{"number":"0.013","isBolded":false,"associatedRows":["MP - DQN ( no MC )","?"],"associatedColumns":["HFO","Return"],"associatedMergedColumns":[]}]}]