[{"caption":"Table 1: Performance of different clustering algorithms \nMethod \nCOIL-20 COIL-100 USPS MNIST \n\nDeep Learning \n\nJULE* (2016) \n1.000 \n0.985 \n0.913 0.913 \nDBC* (2017) \n0.895 \n0.905 \n0.724 0.917 \nIEC* (2016) \n-\n0.787 \n0.641 0.542 \nDEPICT* (2017) \n-\n-\n0.927 0.917 \nAEC* (2013) \n-\n-\n0.651 0.669 \nNMF-D* (2014) \n0.692 \n0.719 \n0.287 0.152 \nTSC-D* (2016) \n0.928 \n-\n-\n0.651 \nDCEC* (2017) \n-\n-\n0.826 0.885 \nSpectralNet* (2018) -\n-\n-\n0.924 \n\nNon-deep learning \n\nICA BSS* (2018) \n0.965 \n0.962 \n0.868 0.824 \nAC-PIC* (2013) \n0.855 \n0.840 \n0.840 0.017 \nK-means* \n0.774 \n0.775 \n0.613 0.490 \nDBSCAN \n0.892 \n0.705 \n0.299 -\n\nOurs \n0.958 \n0.926** \n0.885 0.864 \n\nTable 1. The NMI scores of various clustering algorithms on different data sets, with top three in bold. \nFor DBSCAN, ? was tuned until the correct number of clusters was obtained. We performed DBSCAN, \nK-Means, and tree-SNE benchmarking; the rest of the values are reported from the original papers. * means \nthe clustering algorithm requires knowing the number of clusters beforehand. ** this was run with ? \u003d 1.3, \nwhereas the rest were run with the default ? \u003d 2. The methods in the table are: Joint Unsupervised Learning \n(JULE, Yang et al. 2016), Discriminatively Boosted Clustering (DBC, Li et al. 2018), Infinite Ensemble \nClustering (IEC, Liu et al. 2016), Autoencoder-based Clustering (AEC, Song et al. 2013), NMF with Deep \nlearning model (NMF-D, Trigeorgis et al. 2014), Task-specific Deep Architecture for Clustering (TSC-D, \nWang et al. 2016), Deep Convolutional Embedded Clustering (DCEC, Guo et al. 2017), SpectralNet \n(Shaham et al. 2018), Independent Component Analysis Blind Source Separation (ICA BSS, Gultepe and \nMakrehchi 2018), Agglomerative Clustering via Path Integral (AC-PIC, Zhang et al. 2013), K-Means, \nDensity-Based Spatial Clustering of Applications with Noise (DBSCAN, Ester et al. 1996). Benchmarking \ndata sets: COIL-20 (Nene et al. 1996a), COIL-100 (Nene et al. 1996b), USPS (Hull 1994), MNIST 60,000 \nsamples (LeCun et al. 1998). \n","rows":["Ours","AC - PIC * ( 2013 )","DCEC * ( 2017 )","TSC - D * ( 2016 )","ICA BSS * ( 2018 )","DBSCAN","AEC * ( 2013 )","-","the clustering algorithm requires knowing the number of clusters beforehand . * * this was run with ? \u003d","IEC * ( 2016 )","SpectralNet * ( 2018 )","0 . 926 * *","DBC * ( 2017 )","K - means *","DEPICT * ( 2017 )","JULE * ( 2016 )","NMF - D * ( 2014 )"],"columns":["COIL - 20","USPS","COIL - 100","MNIST","Table 1 : Performance of different clustering algorithms"],"mergedAllColumns":["K - Means , and tree - SNE benchmarking ; the rest of the values are reported from the original papers . * means","Non - deep learning","-","Deep Learning"],"numberCells":[{"number":"0.868","isBolded":false,"associatedRows":["ICA BSS * ( 2018 )","-","0 . 926 * *"],"associatedColumns":["Table 1 : Performance of different clustering algorithms","USPS"],"associatedMergedColumns":["Non - deep learning"]},{"number":"0.705","isBolded":false,"associatedRows":["DBSCAN","-"],"associatedColumns":["Table 1 : Performance of different clustering algorithms","COIL - 100"],"associatedMergedColumns":["Non - deep learning"]},{"number":"0.613","isBolded":false,"associatedRows":["K - means *","-","0 . 926 * *"],"associatedColumns":["Table 1 : Performance of different clustering algorithms","USPS"],"associatedMergedColumns":["Non - deep learning"]},{"number":"0.885","isBolded":false,"associatedRows":["Ours","-","0 . 926 * *"],"associatedColumns":["Table 1 : Performance of different clustering algorithms","USPS"],"associatedMergedColumns":["-"]},{"number":"0.917","isBolded":false,"associatedRows":["DBC * ( 2017 )","-","-","-"],"associatedColumns":["Table 1 : Performance of different clustering algorithms","MNIST"],"associatedMergedColumns":["Deep Learning"]},{"number":"0.965","isBolded":false,"associatedRows":["ICA BSS * ( 2018 )"],"associatedColumns":["Table 1 : Performance of different clustering algorithms","COIL - 20"],"associatedMergedColumns":["Non - deep learning"]},{"number":"0.895","isBolded":false,"associatedRows":["DBC * ( 2017 )"],"associatedColumns":["Table 1 : Performance of different clustering algorithms","COIL - 20"],"associatedMergedColumns":["Deep Learning"]},{"number":"0.917","isBolded":false,"associatedRows":["DEPICT * ( 2017 )","-","-","-"],"associatedColumns":["Table 1 : Performance of different clustering algorithms","MNIST"],"associatedMergedColumns":["Deep Learning"]},{"number":"0.787","isBolded":false,"associatedRows":["IEC * ( 2016 )","-"],"associatedColumns":["Table 1 : Performance of different clustering algorithms","COIL - 100"],"associatedMergedColumns":["Deep Learning"]},{"number":"0.490","isBolded":false,"associatedRows":["K - means *","-","0 . 926 * *","-"],"associatedColumns":["Table 1 : Performance of different clustering algorithms","MNIST"],"associatedMergedColumns":["Non - deep learning"]},{"number":"1.000","isBolded":false,"associatedRows":["JULE * ( 2016 )"],"associatedColumns":["Table 1 : Performance of different clustering algorithms","COIL - 20"],"associatedMergedColumns":["Deep Learning"]},{"number":"0.913","isBolded":false,"associatedRows":["JULE * ( 2016 )","-","-"],"associatedColumns":["Table 1 : Performance of different clustering algorithms","USPS"],"associatedMergedColumns":["Deep Learning"]},{"number":"0.724","isBolded":false,"associatedRows":["DBC * ( 2017 )","-","-"],"associatedColumns":["Table 1 : Performance of different clustering algorithms","USPS"],"associatedMergedColumns":["Deep Learning"]},{"number":"0.774","isBolded":false,"associatedRows":["K - means *"],"associatedColumns":["Table 1 : Performance of different clustering algorithms","COIL - 20"],"associatedMergedColumns":["Non - deep learning"]},{"number":"0.299","isBolded":false,"associatedRows":["DBSCAN","-","0 . 926 * *"],"associatedColumns":["Table 1 : Performance of different clustering algorithms","USPS"],"associatedMergedColumns":["Non - deep learning"]},{"number":"0.864","isBolded":false,"associatedRows":["Ours","-","0 . 926 * *","-"],"associatedColumns":["Table 1 : Performance of different clustering algorithms","MNIST"],"associatedMergedColumns":["-"]},{"number":"0.913","isBolded":false,"associatedRows":["JULE * ( 2016 )","-","-","-"],"associatedColumns":["Table 1 : Performance of different clustering algorithms","MNIST"],"associatedMergedColumns":["Deep Learning"]},{"number":"0.927","isBolded":false,"associatedRows":["DEPICT * ( 2017 )","-","-"],"associatedColumns":["Table 1 : Performance of different clustering algorithms","USPS"],"associatedMergedColumns":["Deep Learning"]},{"number":"0.152","isBolded":false,"associatedRows":["NMF - D * ( 2014 )","-","-","-"],"associatedColumns":["Table 1 : Performance of different clustering algorithms","MNIST"],"associatedMergedColumns":["Deep Learning"]},{"number":"0.017","isBolded":false,"associatedRows":["AC - PIC * ( 2013 )","-","0 . 926 * *","-"],"associatedColumns":["Table 1 : Performance of different clustering algorithms","MNIST"],"associatedMergedColumns":["Non - deep learning"]},{"number":"0.824","isBolded":false,"associatedRows":["ICA BSS * ( 2018 )","-","0 . 926 * *","-"],"associatedColumns":["Table 1 : Performance of different clustering algorithms","MNIST"],"associatedMergedColumns":["Non - deep learning"]},{"number":"0.542","isBolded":false,"associatedRows":["IEC * ( 2016 )","-","-","-"],"associatedColumns":["Table 1 : Performance of different clustering algorithms","MNIST"],"associatedMergedColumns":["Deep Learning"]},{"number":"0.287","isBolded":false,"associatedRows":["NMF - D * ( 2014 )","-","-"],"associatedColumns":["Table 1 : Performance of different clustering algorithms","USPS"],"associatedMergedColumns":["Deep Learning"]},{"number":"0.958","isBolded":false,"associatedRows":["Ours"],"associatedColumns":["Table 1 : Performance of different clustering algorithms","COIL - 20"],"associatedMergedColumns":["-"]},{"number":"0.985","isBolded":false,"associatedRows":["JULE * ( 2016 )","-"],"associatedColumns":["Table 1 : Performance of different clustering algorithms","COIL - 100"],"associatedMergedColumns":["Deep Learning"]},{"number":"0.826","isBolded":false,"associatedRows":["DCEC * ( 2017 )","-","-"],"associatedColumns":["Table 1 : Performance of different clustering algorithms","USPS"],"associatedMergedColumns":["Deep Learning"]},{"number":"0.855","isBolded":false,"associatedRows":["AC - PIC * ( 2013 )"],"associatedColumns":["Table 1 : Performance of different clustering algorithms","COIL - 20"],"associatedMergedColumns":["Non - deep learning"]},{"number":"0.692","isBolded":false,"associatedRows":["NMF - D * ( 2014 )"],"associatedColumns":["Table 1 : Performance of different clustering algorithms","COIL - 20"],"associatedMergedColumns":["Deep Learning"]},{"number":"0.928","isBolded":false,"associatedRows":["TSC - D * ( 2016 )"],"associatedColumns":["Table 1 : Performance of different clustering algorithms","COIL - 20"],"associatedMergedColumns":["Deep Learning"]},{"number":"0.924","isBolded":false,"associatedRows":["SpectralNet * ( 2018 )","-","-","-"],"associatedColumns":["Table 1 : Performance of different clustering algorithms","MNIST"],"associatedMergedColumns":["Deep Learning"]},{"number":"0.962","isBolded":false,"associatedRows":["ICA BSS * ( 2018 )","-"],"associatedColumns":["Table 1 : Performance of different clustering algorithms","COIL - 100"],"associatedMergedColumns":["Non - deep learning"]},{"number":"1.3,","isBolded":true,"associatedRows":["the clustering algorithm requires knowing the number of clusters beforehand . * * this was run with ? \u003d"],"associatedColumns":["Table 1 : Performance of different clustering algorithms","MNIST"],"associatedMergedColumns":["K - Means , and tree - SNE benchmarking ; the rest of the values are reported from the original papers . * means"]},{"number":"0.719","isBolded":false,"associatedRows":["NMF - D * ( 2014 )","-"],"associatedColumns":["Table 1 : Performance of different clustering algorithms","COIL - 100"],"associatedMergedColumns":["Deep Learning"]},{"number":"0.892","isBolded":false,"associatedRows":["DBSCAN"],"associatedColumns":["Table 1 : Performance of different clustering algorithms","COIL - 20"],"associatedMergedColumns":["Non - deep learning"]},{"number":"0.669","isBolded":false,"associatedRows":["AEC * ( 2013 )","-","-","-"],"associatedColumns":["Table 1 : Performance of different clustering algorithms","MNIST"],"associatedMergedColumns":["Deep Learning"]},{"number":"0.840","isBolded":false,"associatedRows":["AC - PIC * ( 2013 )","-","0 . 926 * *"],"associatedColumns":["Table 1 : Performance of different clustering algorithms","USPS"],"associatedMergedColumns":["Non - deep learning"]},{"number":"0.651","isBolded":false,"associatedRows":["TSC - D * ( 2016 )","-","-","-"],"associatedColumns":["Table 1 : Performance of different clustering algorithms","MNIST"],"associatedMergedColumns":["Deep Learning"]},{"number":"0.905","isBolded":false,"associatedRows":["DBC * ( 2017 )","-"],"associatedColumns":["Table 1 : Performance of different clustering algorithms","COIL - 100"],"associatedMergedColumns":["Deep Learning"]},{"number":"0.641","isBolded":false,"associatedRows":["IEC * ( 2016 )","-","-"],"associatedColumns":["Table 1 : Performance of different clustering algorithms","USPS"],"associatedMergedColumns":["Deep Learning"]},{"number":"0.651","isBolded":false,"associatedRows":["AEC * ( 2013 )","-","-"],"associatedColumns":["Table 1 : Performance of different clustering algorithms","USPS"],"associatedMergedColumns":["Deep Learning"]},{"number":"0.840","isBolded":false,"associatedRows":["AC - PIC * ( 2013 )","-"],"associatedColumns":["Table 1 : Performance of different clustering algorithms","COIL - 100"],"associatedMergedColumns":["Non - deep learning"]},{"number":"0.775","isBolded":false,"associatedRows":["K - means *","-"],"associatedColumns":["Table 1 : Performance of different clustering algorithms","COIL - 100"],"associatedMergedColumns":["Non - deep learning"]},{"number":"0.885","isBolded":false,"associatedRows":["DCEC * ( 2017 )","-","-","-"],"associatedColumns":["Table 1 : Performance of different clustering algorithms","MNIST"],"associatedMergedColumns":["Deep Learning"]}]}]