[{"caption":"Table 1). Especially, the proposed method is much \n\nMethod \nAcc(%) \nFP \nFN \nInference time (msec) \nNetworks Post-pro. \n\n ? Baseline (Push + Pull) [8] \n96.42 0.0654 0.0195 \n6.62 \n ? 498 \n\n ? Baseline (SE) [7] \n95.96 0.0799 0.0261 \nN/A \nN/A \n\nOurs (SE + FG) \n96.20 0.0598 0.0256 \nN/A \nN/A \n\nOurs (SE + FG + BS + Push) 96.58 0.0540 0.0177 \n6.64 \n3.20 \n\nTable 1: TuSimple benchmark results for an image size of 1280?720. Push, Pull, SE, \nFG and BS are abbreviations for inter-cluster push, intra-cluser pull, spatial embedding, \nthe embedding loss only for foreground pixels and bandwidth saturation.  ? denotes our \nre-implementation of the baseline.  ? denotes adoption of DBSCAN for post-processing. \nThe inference time is measured on NVIDIA V100 and Xeon Silver 4114. \n","rows":["Ours ( SE + FG + BS + Push )","Baseline ( Push + Pull ) [ 8 ]","Baseline ( SE ) [ 7 ]","Ours ( SE + FG )"],"columns":["?","Networks","?","N / A","FN","FP","Acc ( % )","Table 1 ) . Especially , the proposed method is much","Post - pro ."],"mergedAllColumns":["?","Inference time ( msec )","498"],"numberCells":[{"number":"96.58","isBolded":true,"associatedRows":["Ours ( SE + FG + BS + Push )"],"associatedColumns":["Table 1 ) . Especially , the proposed method is much","Acc ( % )","Networks","?","N / A","N / A"],"associatedMergedColumns":["?"]},{"number":"0.0195","isBolded":false,"associatedRows":["Baseline ( Push + Pull ) [ 8 ]"],"associatedColumns":["Table 1 ) . Especially , the proposed method is much","FN","Networks"],"associatedMergedColumns":["Inference time ( msec )"]},{"number":"0.0598","isBolded":false,"associatedRows":["Ours ( SE + FG )"],"associatedColumns":["Table 1 ) . Especially , the proposed method is much","FP","Networks","?","N / A"],"associatedMergedColumns":["?"]},{"number":"3.20","isBolded":true,"associatedRows":["Ours ( SE + FG + BS + Push )"],"associatedColumns":["Table 1 ) . Especially , the proposed method is much","FN","Post - pro .","?","N / A","N / A"],"associatedMergedColumns":["?"]},{"number":"0.0654","isBolded":false,"associatedRows":["Baseline ( Push + Pull ) [ 8 ]"],"associatedColumns":["Table 1 ) . Especially , the proposed method is much","FP","Networks"],"associatedMergedColumns":["Inference time ( msec )"]},{"number":"0.0540","isBolded":true,"associatedRows":["Ours ( SE + FG + BS + Push )"],"associatedColumns":["Table 1 ) . Especially , the proposed method is much","FP","Networks","?","N / A","N / A"],"associatedMergedColumns":["?"]},{"number":"0.0177","isBolded":true,"associatedRows":["Ours ( SE + FG + BS + Push )"],"associatedColumns":["Table 1 ) . Especially , the proposed method is much","FN","Networks","?","N / A","N / A"],"associatedMergedColumns":["?"]},{"number":"6.62","isBolded":false,"associatedRows":["Baseline ( Push + Pull ) [ 8 ]"],"associatedColumns":["Table 1 ) . Especially , the proposed method is much","FN","Networks"],"associatedMergedColumns":["Inference time ( msec )"]},{"number":"0.0261","isBolded":false,"associatedRows":["Baseline ( SE ) [ 7 ]"],"associatedColumns":["Table 1 ) . Especially , the proposed method is much","FN","Networks","?"],"associatedMergedColumns":["498"]},{"number":"0.0256","isBolded":false,"associatedRows":["Ours ( SE + FG )"],"associatedColumns":["Table 1 ) . Especially , the proposed method is much","FN","Networks","?","N / A"],"associatedMergedColumns":["?"]},{"number":"95.96","isBolded":false,"associatedRows":["Baseline ( SE ) [ 7 ]"],"associatedColumns":["Table 1 ) . Especially , the proposed method is much","Acc ( % )","Networks","?"],"associatedMergedColumns":["498"]},{"number":"0.0799","isBolded":false,"associatedRows":["Baseline ( SE ) [ 7 ]"],"associatedColumns":["Table 1 ) . Especially , the proposed method is much","FP","Networks","?"],"associatedMergedColumns":["498"]},{"number":"6.64","isBolded":false,"associatedRows":["Ours ( SE + FG + BS + Push )"],"associatedColumns":["Table 1 ) . Especially , the proposed method is much","FN","Networks","?","N / A","N / A"],"associatedMergedColumns":["?"]},{"number":"96.20","isBolded":false,"associatedRows":["Ours ( SE + FG )"],"associatedColumns":["Table 1 ) . Especially , the proposed method is much","Acc ( % )","Networks","?","N / A"],"associatedMergedColumns":["?"]},{"number":"96.42","isBolded":false,"associatedRows":["Baseline ( Push + Pull ) [ 8 ]"],"associatedColumns":["Table 1 ) . Especially , the proposed method is much","Acc ( % )","Networks"],"associatedMergedColumns":["Inference time ( msec )"]}]}]