[{"caption":"selfie2anime \n\ncat2dog \nDFID ? FID ? LPIPS ? DFID ? FID ? LPIPS ? \nGNR \n35.6 \n34.4 \n0.505 \n26.1 \n26.9 \n0.569 \nDRIT++ \n94.6 \n63.8 \n0.201 \n160.1 \n91.5 \n0.231 \nCouncilGAN \n56.2 \n38.1 \n0.430 \n172.5 \n90.8 \n0.298 \nStarGANv2 \n83.0 \n59.8 \n0.427 \n53.6 \n44.2 \n0.530 \n\nTable 1. Quantitative Comparisons: We compare GNR with other SoTA frameworks. DFID compares the distribution of a single image \ntranslated with different styles with the distribution of real images, thus focus on output diversity. FID compares general image quality \nwhile LPIPS also focuses on output diversity. Our method shows significant improvements across all metrics, especially on the Diversity \nFID and LPIPS metric which measures diversity. \n\n","rows":["DRIT++","CouncilGAN","GNR","StarGANv2"],"columns":["DFID ?","FID ?","cat2dog","LPIPS ?","selfie2anime"],"mergedAllColumns":[],"numberCells":[{"number":"91.5","isBolded":false,"associatedRows":["DRIT++"],"associatedColumns":["cat2dog","FID ?"],"associatedMergedColumns":[]},{"number":"44.2","isBolded":false,"associatedRows":["StarGANv2"],"associatedColumns":["cat2dog","FID ?"],"associatedMergedColumns":[]},{"number":"56.2","isBolded":false,"associatedRows":["CouncilGAN"],"associatedColumns":["selfie2anime","DFID ?"],"associatedMergedColumns":[]},{"number":"38.1","isBolded":false,"associatedRows":["CouncilGAN"],"associatedColumns":["selfie2anime","FID ?"],"associatedMergedColumns":[]},{"number":"26.1","isBolded":true,"associatedRows":["GNR"],"associatedColumns":["cat2dog"],"associatedMergedColumns":[]},{"number":"83.0","isBolded":false,"associatedRows":["StarGANv2"],"associatedColumns":["selfie2anime","DFID ?"],"associatedMergedColumns":[]},{"number":"94.6","isBolded":false,"associatedRows":["DRIT++"],"associatedColumns":["selfie2anime","DFID ?"],"associatedMergedColumns":[]},{"number":"0.430","isBolded":false,"associatedRows":["CouncilGAN"],"associatedColumns":["selfie2anime","LPIPS ?"],"associatedMergedColumns":[]},{"number":"0.231","isBolded":false,"associatedRows":["DRIT++"],"associatedColumns":["cat2dog","LPIPS ?"],"associatedMergedColumns":[]},{"number":"59.8","isBolded":false,"associatedRows":["StarGANv2"],"associatedColumns":["selfie2anime","FID ?"],"associatedMergedColumns":[]},{"number":"0.201","isBolded":false,"associatedRows":["DRIT++"],"associatedColumns":["selfie2anime","LPIPS ?"],"associatedMergedColumns":[]},{"number":"53.6","isBolded":false,"associatedRows":["StarGANv2"],"associatedColumns":["cat2dog","DFID ?"],"associatedMergedColumns":[]},{"number":"35.6","isBolded":true,"associatedRows":["GNR"],"associatedColumns":["selfie2anime"],"associatedMergedColumns":[]},{"number":"0.427","isBolded":false,"associatedRows":["StarGANv2"],"associatedColumns":["selfie2anime","LPIPS ?"],"associatedMergedColumns":[]},{"number":"0.569","isBolded":true,"associatedRows":["GNR"],"associatedColumns":["cat2dog"],"associatedMergedColumns":[]},{"number":"172.5","isBolded":false,"associatedRows":["CouncilGAN"],"associatedColumns":["cat2dog","DFID ?"],"associatedMergedColumns":[]},{"number":"0.505","isBolded":true,"associatedRows":["GNR"],"associatedColumns":["selfie2anime"],"associatedMergedColumns":[]},{"number":"0.530","isBolded":false,"associatedRows":["StarGANv2"],"associatedColumns":["cat2dog","LPIPS ?"],"associatedMergedColumns":[]},{"number":"26.9","isBolded":true,"associatedRows":["GNR"],"associatedColumns":["cat2dog"],"associatedMergedColumns":[]},{"number":"160.1","isBolded":false,"associatedRows":["DRIT++"],"associatedColumns":["cat2dog","DFID ?"],"associatedMergedColumns":[]},{"number":"34.4","isBolded":true,"associatedRows":["GNR"],"associatedColumns":["selfie2anime"],"associatedMergedColumns":[]},{"number":"63.8","isBolded":false,"associatedRows":["DRIT++"],"associatedColumns":["selfie2anime","FID ?"],"associatedMergedColumns":[]},{"number":"0.298","isBolded":false,"associatedRows":["CouncilGAN"],"associatedColumns":["cat2dog","LPIPS ?"],"associatedMergedColumns":[]},{"number":"90.8","isBolded":false,"associatedRows":["CouncilGAN"],"associatedColumns":["cat2dog","FID ?"],"associatedMergedColumns":[]}]}]